Workbook

Sheet Precios
A1: Lista de precios interna — Food Prep (NO compartir con clientes)
A2: Azul = dato que puedes cambiar (costo). Amarillo = aumento manual opcional (ej. 0.70 = +70 %); si lo dejas vacío se usa la regla de la hoja 'Reglas'. Verde = viene de la hoja 'Reglas'. Negro = fórmula.
A4: # | B4: Categoría | C4: Producto (como sale en la app) | D4: Nombre en catálogo | E4: Costo (MXN) | F4: Aumento por regla | G4: Aumento manual (opcional) | H4: Aumento aplicado | I4: Precio sin redondear (MXN) | J4: Precio de venta (MXN) | K4: Ganancia por pieza (MXN) | L4: Margen sobre venta
A5: 1 | B5: Licuadoras | C5: LIC INFINYFORCE XL 10v ROJA | D5: Licuadora Infinyforce XL Roja 10 vel. | E5: 362.5 | F5: =INDEX(Reglas!$C$5:$C$8,MATCH(E5,Reglas!$A$5:$A$8,1)) -> 0.65 | H5: =IF(G5="",F5,G5) -> 0.65 | I5: =E5*(1+H5) -> 598.125 | J5: =IF(I5<1000,CEILING(I5,10)-1,CEILING(I5,50)-1) -> 599 | K5: =J5-E5 -> 236.5 | L5: =IF(J5=0,"",K5/J5) -> 0.39482471
A6: 2 | B6: Licuadoras | C6: LIC INFINYFORCE XL 12V BL | D6: Licuadora Infinyforce XL Blanca 12 vel. | E6: 384.06 | F6: =INDEX(Reglas!$C$5:$C$8,MATCH(E6,Reglas!$A$5:$A$8,1)) -> 0.65 | H6: =IF(G6="",F6,G6) -> 0.65 | I6: =E6*(1+H6) -> 633.699 | J6: =IF(I6<1000,CEILING(I6,10)-1,CEILING(I6,50)-1) -> 639 | K6: =J6-E6 -> 254.94 | L6: =IF(J6=0,"",K6/J6) -> 0.39896714
A7: 3 | B7: Licuadoras | C7: LIC INFINYFORCE XL 12V RED | D7: Licuadora Infinyforce XL Roja 12 vel. | E7: 384.59 | F7: =INDEX(Reglas!$C$5:$C$8,MATCH(E7,Reglas!$A$5:$A$8,1)) -> 0.65 | H7: =IF(G7="",F7,G7) -> 0.65 | I7: =E7*(1+H7) -> 634.5735 | J7: =IF(I7<1000,CEILING(I7,10)-1,CEILING(I7,50)-1) -> 639 | K7: =J7-E7 -> 254.41 | L7: =IF(J7=0,"",K7/J7) -> 0.39813772
A8: 4 | B8: Licuadoras | C8: LIC INFINYFORCE XL 14V NEGRA | D8: Licuadora Infinyforce XL Negra 14 vel. | E8: 419.93 | F8: =INDEX(Reglas!$C$5:$C$8,MATCH(E8,Reglas!$A$5:$A$8,1)) -> 0.65 | H8: =IF(G8="",F8,G8) -> 0.65 | I8: =E8*(1+H8) -> 692.8845 | J8: =IF(I8<1000,CEILING(I8,10)-1,CEILING(I8,50)-1) -> 699 | K8: =J8-E8 -> 279.07 | L8: =IF(J8=0,"",K8/J8) -> 0.39924177
A9: 5 | B9: Licuadoras | C9: LIC ULTRAFORCE+ 2V MX | D9: Licuadora Ultraforce+ 2 vel. | E9: 525.56 | F9: =INDEX(Reglas!$C$5:$C$8,MATCH(E9,Reglas!$A$5:$A$8,1)) -> 0.65 | H9: =IF(G9="",F9,G9) -> 0.65 | I9: =E9*(1+H9) -> 867.174 | J9: =IF(I9<1000,CEILING(I9,10)-1,CEILING(I9,50)-1) -> 869 | K9: =J9-E9 -> 343.44 | L9: =IF(J9=0,"",K9/J9) -> 0.39521289
A10: 6 | B10: Licuadoras | C10: LIC ULTRAFORCE+ 8V MX | D10: Licuadora Ultraforce+ 8 vel. | E10: 550.83 | F10: =INDEX(Reglas!$C$5:$C$8,MATCH(E10,Reglas!$A$5:$A$8,1)) -> 0.65 | H10: =IF(G10="",F10,G10) -> 0.65 | I10: =E10*(1+H10) -> 908.8695 | J10: =IF(I10<1000,CEILING(I10,10)-1,CEILING(I10,50)-1) -> 909 | K10: =J10-E10 -> 358.17 | L10: =IF(J10=0,"",K10/J10) -> 0.3940264
A11: 7 | B11: Licuadoras de alto rendimiento | C11: LIC. ULTRAFORCE PRO INOX | D11: Licuadora Ultraforce Pro Inox | E11: 950.19 | F11: =INDEX(Reglas!$C$5:$C$8,MATCH(E11,Reglas!$A$5:$A$8,1)) -> 0.55 | H11: =IF(G11="",F11,G11) -> 0.55 | I11: =E11*(1+H11) -> 1472.7945 | J11: =IF(I11<1000,CEILING(I11,10)-1,CEILING(I11,50)-1) -> 1499 | K11: =J11-E11 -> 548.81 | L11: =IF(J11=0,"",K11/J11) -> 0.36611741
A12: 8 | B12: Licuadoras de alto rendimiento | C12: LIC. ULTRAFORCE PRO NEGRA | D12: Licuadora Ultraforce Pro Negra | E12: 978.67 | F12: =INDEX(Reglas!$C$5:$C$8,MATCH(E12,Reglas!$A$5:$A$8,1)) -> 0.55 | H12: =IF(G12="",F12,G12) -> 0.55 | I12: =E12*(1+H12) -> 1516.9385 | J12: =IF(I12<1000,CEILING(I12,10)-1,CEILING(I12,50)-1) -> 1549 | K12: =J12-E12 -> 570.33 | L12: =IF(J12=0,"",K12/J12) -> 0.36819238
A13: 9 | B13: Licuadoras de alto rendimiento | C13: LIC. INFINYMIX | D13: Licuadora Infinymix | E13: 1608.09 | F13: =INDEX(Reglas!$C$5:$C$8,MATCH(E13,Reglas!$A$5:$A$8,1)) -> 0.45 | H13: =IF(G13="",F13,G13) -> 0.45 | I13: =E13*(1+H13) -> 2331.7305 | J13: =IF(I13<1000,CEILING(I13,10)-1,CEILING(I13,50)-1) -> 2349 | K13: =J13-E13 -> 740.91 | L13: =IF(J13=0,"",K13/J13) -> 0.31541507
A14: 10 | B14: Licuadoras de alto rendimiento | C14: LIC. ULTRAFORCE COOK | D14: Licuadora Ultraforce Cook | E14: 1645.59 | F14: =INDEX(Reglas!$C$5:$C$8,MATCH(E14,Reglas!$A$5:$A$8,1)) -> 0.45 | H14: =IF(G14="",F14,G14) -> 0.45 | I14: =E14*(1+H14) -> 2386.1055 | J14: =IF(I14<1000,CEILING(I14,10)-1,CEILING(I14,50)-1) -> 2399 | K14: =J14-E14 -> 753.41 | L14: =IF(J14=0,"",K14/J14) -> 0.31405169
A15: 11 | B15: Licuadoras personales | C15: LIGHT MIX EUCALYPTUS | D15: Licuadora portátil Light Mix Eucalyptus | E15: 321.42 | F15: =INDEX(Reglas!$C$5:$C$8,MATCH(E15,Reglas!$A$5:$A$8,1)) -> 0.65 | H15: =IF(G15="",F15,G15) -> 0.65 | I15: =E15*(1+H15) -> 530.343 | J15: =IF(I15<1000,CEILING(I15,10)-1,CEILING(I15,50)-1) -> 539 | K15: =J15-E15 -> 217.58 | L15: =IF(J15=0,"",K15/J15) -> 0.40367347
A16: 12 | B16: Licuadoras personales | C16: LIGHT MIX NEST | D16: Licuadora portátil Light Mix Nest | E16: 321.42 | F16: =INDEX(Reglas!$C$5:$C$8,MATCH(E16,Reglas!$A$5:$A$8,1)) -> 0.65 | H16: =IF(G16="",F16,G16) -> 0.65 | I16: =E16*(1+H16) -> 530.343 | J16: =IF(I16<1000,CEILING(I16,10)-1,CEILING(I16,50)-1) -> 539 | K16: =J16-E16 -> 217.58 | L16: =IF(J16=0,"",K16/J16) -> 0.40367347
... A28: 24 | B28: Exprimidores y extractores | C28: SLOW JUICER JUICE n CLEAN | D28: Extractor en frío Slow Juicer Juice n Clean | E28: 1405.86 | F28: =INDEX(Reglas!$C$5:$C$8,MATCH(E28,Reglas!$A$5:$A$8,1)) -> 0.45 | H28: =IF(G28="",F28,G28) -> 0.45 | I28: =E28*(1+H28) -> 2038.497 | J28: =IF(I28<1000,CEILING(I28,10)-1,CEILING(I28,50)-1) -> 2049 | K28: =J28-E28 -> 643.14 | L28: =IF(J28=0,"",K28/J28) -> 0.31387994
D29: TOTAL (1 pieza de cada uno) | E29: =SUM(E5:E28) -> 14077.98 | J29: =SUM(J5:J28) -> 22286 | K29: =SUM(K5:K28) -> 8208.02 | L29: =IF(J29=0,"",K29/J29) -> 0.36830387

Sheet Reglas
A1: Reglas de aumento por rango de costo
A2: Celdas azules = puedes cambiarlas. El Excel recalcula todos los precios solo.
A4: Costo desde (MXN) | B4: Rango | C4: Aumento %
A5: 0 | B5: $0 a $299.99 | C5: 0.8
A6: 300 | B6: $300 a $699.99 | C6: 0.65
A7: 700 | B7: $700 a $1,199.99 | C7: 0.55
A8: 1200 | B8: $1,200 en adelante | C8: 0.45
A10: Redondeo: si el precio queda abajo de $1,000 se sube al siguiente número terminado en 9 (ej. $593 → $599).
A11: Si queda en $1,000 o más se sube al siguiente terminado en 49 o 99 (ej. $1,473 → $1,499).
A12: Criterio: % más alto en productos baratos (para que la ganancia en pesos valga la pena) y más bajo en los caros
A13: (para que el precio siga siendo atractivo frente a tienda). Supuestos propuestos por Claude; ajústalos a tu gusto.
A14: La columna 'Rango' es solo texto descriptivo: si cambias 'Costo desde', actualízala a mano.

Sheet Pendientes
A1: Productos con datos incompletos (no salen en el catálogo)
A3: Producto (app) | B3: Costo visto (MXN) | C3: Qué falta
A4: QUICK CHEF+ | C4: Precio (no se ve en la foto)
A5: (nombre cortado en la foto) | B5: 239.56 | C5: Nombre (cortado en la foto)
A6: (nombre cortado en la foto) | B6: 556.04 | C6: Nombre (cortado en la foto)
A8: La app dice 'Artículos encontrados: 37' en Food Prep; en las fotos se alcanzan a ver 27. Manda capturas de los que faltan para completarlo.
