Workbook

Sheet Precios
A1: Lista de precios interna (NO compartir con clientes)
A2: Azul = dato que puedes cambiar (costo). Amarillo = aumento manual opcional (ej. 0.70 = +70 %); si lo dejas vacío se usa la regla de la hoja 'Reglas'. Verde = viene de la hoja 'Reglas'. Negro = fórmula.
A4: # | B4: Pestaña app | C4: Categoría | D4: Producto (como sale en la app) | E4: Nombre en catálogo | F4: Costo (MXN) | G4: Aumento por regla | H4: Aumento manual (opcional) | I4: Precio mínimo del rango (MXN) | J4: Precio sin redondear (MXN) | K4: Precio de venta (MXN) | L4: Ganancia por pieza (MXN) | M4: Margen sobre venta | N4: Aumento real
A5: 1 | B5: CW & BW | C5: Sartenes | D5: SARTEN 20 CM RJ CHARACTER | E5: Sartén Character Roja 20 cm | F5: 96.1 | G5: =INDEX(Reglas!$C$5:$C$8,MATCH(F5,Reglas!$A$5:$A$8,1)) -> 0.8 | I5: =INDEX(Reglas!$D$5:$D$8,MATCH(F5,Reglas!$A$5:$A$8,1)) -> 0 | J5: =IF(H5="",MAX(F5*(1+G5),I5),F5*(1+H5)) -> 172.98 | K5: =IF(J5<1000,CEILING(J5,10)-1,CEILING(J5,50)-1) -> 179 | L5: =K5-F5 -> 82.9 | M5: =IF(K5=0,"",L5/K5) -> 0.46312849 | N5: =IF(F5=0,"",K5/F5-1) -> 0.86264308
A6: 2 | B6: CW & BW | C6: Sartenes | D6: SARTEN 20 CM RJ VITAL FR | E6: Sartén Vital Roja 20 cm | F6: 126.08 | G6: =INDEX(Reglas!$C$5:$C$8,MATCH(F6,Reglas!$A$5:$A$8,1)) -> 0.8 | I6: =INDEX(Reglas!$D$5:$D$8,MATCH(F6,Reglas!$A$5:$A$8,1)) -> 0 | J6: =IF(H6="",MAX(F6*(1+G6),I6),F6*(1+H6)) -> 226.944 | K6: =IF(J6<1000,CEILING(J6,10)-1,CEILING(J6,50)-1) -> 229 | L6: =K6-F6 -> 102.92 | M6: =IF(K6=0,"",L6/K6) -> 0.44943231 | N6: =IF(F6=0,"",K6/F6-1) -> 0.81630711
A7: 3 | B7: CW & BW | C7: Sartenes | D7: SARTEN 28 CM RJ CHARACTER | E7: Sartén Character Roja 28 cm | F7: 141.55 | G7: =INDEX(Reglas!$C$5:$C$8,MATCH(F7,Reglas!$A$5:$A$8,1)) -> 0.8 | I7: =INDEX(Reglas!$D$5:$D$8,MATCH(F7,Reglas!$A$5:$A$8,1)) -> 0 | J7: =IF(H7="",MAX(F7*(1+G7),I7),F7*(1+H7)) -> 254.79 | K7: =IF(J7<1000,CEILING(J7,10)-1,CEILING(J7,50)-1) -> 259 | L7: =K7-F7 -> 117.45 | M7: =IF(K7=0,"",L7/K7) -> 0.4534749 | N7: =IF(F7=0,"",K7/F7-1) -> 0.82974214
A8: 4 | B8: CW & BW | C8: Sartenes | D8: SARTEN 24 CM RJ VITAL FR | E8: Sartén Vital Roja 24 cm | F8: 146.67 | G8: =INDEX(Reglas!$C$5:$C$8,MATCH(F8,Reglas!$A$5:$A$8,1)) -> 0.8 | I8: =INDEX(Reglas!$D$5:$D$8,MATCH(F8,Reglas!$A$5:$A$8,1)) -> 0 | J8: =IF(H8="",MAX(F8*(1+G8),I8),F8*(1+H8)) -> 264.006 | K8: =IF(J8<1000,CEILING(J8,10)-1,CEILING(J8,50)-1) -> 269 | L8: =K8-F8 -> 122.33 | M8: =IF(K8=0,"",L8/K8) -> 0.45475836 | N8: =IF(F8=0,"",K8/F8-1) -> 0.83404923
A9: 5 | B9: CW & BW | C9: Sartenes | D9: SARTEN 26 CM RJ VITAL FR | E9: Sartén Vital Roja 26 cm | F9: 158.83 | G9: =INDEX(Reglas!$C$5:$C$8,MATCH(F9,Reglas!$A$5:$A$8,1)) -> 0.8 | I9: =INDEX(Reglas!$D$5:$D$8,MATCH(F9,Reglas!$A$5:$A$8,1)) -> 0 | J9: =IF(H9="",MAX(F9*(1+G9),I9),F9*(1+H9)) -> 285.894 | K9: =IF(J9<1000,CEILING(J9,10)-1,CEILING(J9,50)-1) -> 289 | L9: =K9-F9 -> 130.17 | M9: =IF(K9=0,"",L9/K9) -> 0.45041522 | N9: =IF(F9=0,"",K9/F9-1) -> 0.8195555
A10: 6 | B10: CW & BW | C10: Sartenes | D10: SARTEN 20 CM TRENDY TITANIUM | E10: Sartén Trendy Titanium 20 cm | F10: 202.07 | G10: =INDEX(Reglas!$C$5:$C$8,MATCH(F10,Reglas!$A$5:$A$8,1)) -> 0.8 | I10: =INDEX(Reglas!$D$5:$D$8,MATCH(F10,Reglas!$A$5:$A$8,1)) -> 0 | J10: =IF(H10="",MAX(F10*(1+G10),I10),F10*(1+H10)) -> 363.726 | K10: =IF(J10<1000,CEILING(J10,10)-1,CEILING(J10,50)-1) -> 369 | L10: =K10-F10 -> 166.93 | M10: =IF(K10=0,"",L10/K10) -> 0.45238482 | N10: =IF(F10=0,"",K10/F10-1) -> 0.82609987
A11: 7 | B11: CW & BW | C11: Sartenes | D11: SARTEN 24 CM TRENDY TITANIUM | E11: Sartén Trendy Titanium 24 cm | F11: 216.46 | G11: =INDEX(Reglas!$C$5:$C$8,MATCH(F11,Reglas!$A$5:$A$8,1)) -> 0.8 | I11: =INDEX(Reglas!$D$5:$D$8,MATCH(F11,Reglas!$A$5:$A$8,1)) -> 0 | J11: =IF(H11="",MAX(F11*(1+G11),I11),F11*(1+H11)) -> 389.628 | K11: =IF(J11<1000,CEILING(J11,10)-1,CEILING(J11,50)-1) -> 389 | L11: =K11-F11 -> 172.54 | M11: =IF(K11=0,"",L11/K11) -> 0.44354756 | N11: =IF(F11=0,"",K11/F11-1) -> 0.79709877
A12: 8 | B12: CW & BW | C12: Sartenes | D12: CREPERA 25 CM HARD TIT EXPERT | E12: Crepera Hard Titanium Expert 25 cm | F12: 229.98 | G12: =INDEX(Reglas!$C$5:$C$8,MATCH(F12,Reglas!$A$5:$A$8,1)) -> 0.8 | I12: =INDEX(Reglas!$D$5:$D$8,MATCH(F12,Reglas!$A$5:$A$8,1)) -> 0 | J12: =IF(H12="",MAX(F12*(1+G12),I12),F12*(1+H12)) -> 413.964 | K12: =IF(J12<1000,CEILING(J12,10)-1,CEILING(J12,50)-1) -> 419 | L12: =K12-F12 -> 189.02 | M12: =IF(K12=0,"",L12/K12) -> 0.45112172 | N12: =IF(F12=0,"",K12/F12-1) -> 0.82189756
A13: 9 | B13: CW & BW | C13: Juegos de sartenes | D13: JGO 20/24/28 CM ROJO CHARACTER | E13: Juego de 3 sartenes Character Rojo | F13: 362.45 | G13: =INDEX(Reglas!$C$5:$C$8,MATCH(F13,Reglas!$A$5:$A$8,1)) -> 0.65 | I13: =INDEX(Reglas!$D$5:$D$8,MATCH(F13,Reglas!$A$5:$A$8,1)) -> 540 | J13: =IF(H13="",MAX(F13*(1+G13),I13),F13*(1+H13)) -> 598.0425 | K13: =IF(J13<1000,CEILING(J13,10)-1,CEILING(J13,50)-1) -> 599 | L13: =K13-F13 -> 236.55 | M13: =IF(K13=0,"",L13/K13) -> 0.39490818 | N13: =IF(F13=0,"",K13/F13-1) -> 0.65264174
A14: 10 | B14: CW & BW | C14: Juegos de sartenes | D14: JGO 12/20/24/26 CM RJO VITAL | E14: Juego de 4 sartenes Vital Rojo | F14: 492.72 | G14: =INDEX(Reglas!$C$5:$C$8,MATCH(F14,Reglas!$A$5:$A$8,1)) -> 0.65 | I14: =INDEX(Reglas!$D$5:$D$8,MATCH(F14,Reglas!$A$5:$A$8,1)) -> 540 | J14: =IF(H14="",MAX(F14*(1+G14),I14),F14*(1+H14)) -> 812.988 | K14: =IF(J14<1000,CEILING(J14,10)-1,CEILING(J14,50)-1) -> 819 | L14: =K14-F14 -> 326.28 | M14: =IF(K14=0,"",L14/K14) -> 0.39838828 | N14: =IF(F14=0,"",K14/F14-1) -> 0.66220166
A15: 11 | B15: CW & BW | C15: Juegos de sartenes | D15: JGO 20/24/28 CM BG TRENDY TITANIUM | E15: Juego de 3 sartenes Trendy Titanium Beige | F15: 705.08 | G15: =INDEX(Reglas!$C$5:$C$8,MATCH(F15,Reglas!$A$5:$A$8,1)) -> 0.55 | I15: =INDEX(Reglas!$D$5:$D$8,MATCH(F15,Reglas!$A$5:$A$8,1)) -> 1155 | J15: =IF(H15="",MAX(F15*(1+G15),I15),F15*(1+H15)) -> 1155 | K15: =IF(J15<1000,CEILING(J15,10)-1,CEILING(J15,50)-1) -> 1199 | L15: =K15-F15 -> 493.92 | M15: =IF(K15=0,"",L15/K15) -> 0.41194329 | N15: =IF(F15=0,"",K15/F15-1) -> 0.70051625
A16: 12 | B16: CW & BW | C16: Baterías de cocina | D16: BAT 9 PZS LIC NEGRA SUPERCOOK V2 | E16: Batería Supercook 9 piezas + licuadora | F16: 866.93 | G16: =INDEX(Reglas!$C$5:$C$8,MATCH(F16,Reglas!$A$5:$A$8,1)) -> 0.55 | I16: =INDEX(Reglas!$D$5:$D$8,MATCH(F16,Reglas!$A$5:$A$8,1)) -> 1155 | J16: =IF(H16="",MAX(F16*(1+G16),I16),F16*(1+H16)) -> 1343.7415 | K16: =IF(J16<1000,CEILING(J16,10)-1,CEILING(J16,50)-1) -> 1349 | L16: =K16-F16 -> 482.07 | M16: =IF(K16=0,"",L16/K16) -> 0.3573536 | N16: =IF(F16=0,"",K16/F16-1) -> 0.55606566
... A43: 39 | B43: Food Prep | C43: Exprimidores y extractores | D43: SLOW JUICER JUICE n CLEAN | E43: Extractor en frío Slow Juicer Juice n Clean | F43: 1405.86 | G43: =INDEX(Reglas!$C$5:$C$8,MATCH(F43,Reglas!$A$5:$A$8,1)) -> 0.45 | I43: =INDEX(Reglas!$D$5:$D$8,MATCH(F43,Reglas!$A$5:$A$8,1)) -> 1860 | J43: =IF(H43="",MAX(F43*(1+G43),I43),F43*(1+H43)) -> 2038.497 | K43: =IF(J43<1000,CEILING(J43,10)-1,CEILING(J43,50)-1) -> 2049 | L43: =K43-F43 -> 643.14 | M43: =IF(K43=0,"",L43/K43) -> 0.31387994 | N43: =IF(F43=0,"",K43/F43-1) -> 0.45747087
E44: TOTAL (1 pieza de cada uno) | F44: =SUM(F5:F43) -> 20784 | K44: =SUM(K5:K43) -> 33331 | L44: =SUM(L5:L43) -> 12547 | M44: =IF(K44=0,"",L44/K44) -> 0.37643635

Sheet Resumen
A1: Resumen por pestaña (1 pieza de cada producto)
A3: Pestaña app | B3: Productos | C3: Inversión (MXN) | D3: Venta (MXN) | E3: Ganancia (MXN) | F3: Margen sobre venta
A4: CW & BW | B4: =COUNTIF(Precios!$B$5:$B$43,A4) -> 15 | C4: =SUMIF(Precios!$B$5:$B$43,A4,Precios!$F$5:$F$43) -> 6706.02 | D4: =SUMIF(Precios!$B$5:$B$43,A4,Precios!$K$5:$K$43) -> 11015 | E4: =SUMIF(Precios!$B$5:$B$43,A4,Precios!$L$5:$L$43) -> 4308.98 | F4: =IF(D4=0,"",E4/D4) -> 0.39119201
A5: Food Prep | B5: =COUNTIF(Precios!$B$5:$B$43,A5) -> 24 | C5: =SUMIF(Precios!$B$5:$B$43,A5,Precios!$F$5:$F$43) -> 14077.98 | D5: =SUMIF(Precios!$B$5:$B$43,A5,Precios!$K$5:$K$43) -> 22316 | E5: =SUMIF(Precios!$B$5:$B$43,A5,Precios!$L$5:$L$43) -> 8238.02 | F5: =IF(D5=0,"",E5/D5) -> 0.36915307
A6: TOTAL | B6: =SUM(B4:B5) -> 39 | C6: =SUM(C4:C5) -> 20784 | D6: =SUM(D4:D5) -> 33331 | E6: =SUM(E4:E5) -> 12547 | F6: =IF(D6=0,"",E6/D6) -> 0.37643635

Sheet Reglas
A1: Reglas de aumento por rango de costo
A2: Celdas azules = puedes cambiarlas. El Excel recalcula todos los precios solo.
A4: Costo desde (MXN) | B4: Rango | C4: Aumento % | D4: Precio mínimo del rango (MXN)
A5: 0 | B5: $0 a $299.99 | C5: 0.8 | D5: 0
A6: 300 | B6: $300 a $699.99 | C6: 0.65 | D6: =A6*(1+C5) -> 540
A7: 700 | B7: $700 a $1,199.99 | C7: 0.55 | D7: =A7*(1+C6) -> 1155
A8: 1200 | B8: $1,200 en adelante | C8: 0.45 | D8: =A8*(1+C7) -> 1860
A10: Redondeo: si el precio queda abajo de $1,000 se sube al siguiente número terminado en 9 (ej. $593 → $599).
A11: Si queda en $1,000 o más se sube al siguiente terminado en 49 o 99 (ej. $1,473 → $1,499).
A12: Precio mínimo del rango: lo que costaría el producto más caro del rango anterior. Así nunca vendes más
A13: barato algo que te costó más (ej. algo de $305 no queda abajo de algo de $299).
A14: Criterio: % más alto en productos baratos (para que la ganancia en pesos valga la pena) y más bajo en los
A15: caros (para que el precio siga siendo atractivo frente a tienda). Supuestos propuestos por Claude; ajústalos.
A16: La columna 'Rango' es solo texto descriptivo: si cambias 'Costo desde', actualízala a mano.

Sheet Pendientes
A1: Productos con datos incompletos (no salen en el catálogo)
A3: Pestaña app | B3: Producto (app) | C3: Costo visto (MXN) | D3: Qué falta
A4: CW & BW | B4: SARTEN 30 CM RJ VITAL FR | D4: Precio (no se ve en la foto)
A5: CW & BW | B5: BATERIA 17 PZS NEGRA EASY CARE | D5: Precio (no se ve en la foto)
A6: Food Prep | B6: QUICK CHEF+ | D6: Precio (no se ve en la foto)
A7: Food Prep | B7: (nombre cortado en la foto) | C7: 239.56 | D7: Nombre (cortado en la foto)
A8: Food Prep | B8: (nombre cortado en la foto) | C8: 556.04 | D8: Nombre (cortado en la foto)
A10: Food Prep: la app dice 37 artículos y en las fotos se ven 27. Manda capturas de los que faltan.
