Workbook

Sheet Léeme
A1: Financiamiento a las empresas en México 2020-2026 — base de datos
A2: Encuesta Trimestral de Evaluación Coyuntural del Mercado Crediticio (Banxico). Versión corregida, octubre 2026.
A4: Qué contiene
A5: Series | B5: Base trimestral del diseño muestral vigente, IV-2020 a III-2026 (III-2026 pendiente de publicación).
A6: Serie completa 2020-2026 | B6: Los 27 trimestres de I-2020 a III-2026. I a III de 2020 vienen de la muestra anterior; desde IV-2020, del diseño vigente. Incluye línea de tendencia.
A7: Resumen anual | B7: Promedio de los trimestres de cada año, 2020-2026, más el dato del IV trimestre para mostrar que no es acumulado.
A8: Por tamaño | B8: Cuadro A gran empresa (más de 100 empleados), Cuadro B pequeñas y medianas (11 a 100), Cuadro C brecha por año. Con gráficas.
A9: Rechazo y costo | B9: Tasa de rechazo e índice de costo (tasas de interés), trimestral y anual, total y por tamaño.
A10: Variables | B10: Qué mide cada variable, en qué unidad está y si es acumulada.
A11: Hipótesis | B11: Hipótesis 2020-2026 y lo que dicen los datos.
A12: Datos de imágenes | B12: Base de datos detrás de cada gráfica de los documentos Word, con su fuente.
A13: Estadísticas | B13: Promedio, desviación, tendencia, correlación con la tasa y fases de política monetaria.
A14: Muestra anterior | B14: Comparación de la muestra anterior (≥450 empresas) con el diseño vigente.
A15: Pendientes | B15: Datos que faltan, por qué y dónde descargarlos.
A16: Verificación / Fuentes | B16: Control de cifras y comunicados usados.
A18: Cómo leer los colores
A19: Azul | B19: Dato capturado de la fuente (comunicado de Banxico o nota citada).
A20: Negro | B20: Fórmula calculada en el libro.
A21: Verde | B21: Vínculo a otra hoja del libro.
A22: Amarillo | B22: Celda pendiente: el dato aún no se publica o no se pudo descargar. Al capturarlo, las fórmulas se actualizan solas.
A24: Unidades
A25: Porcentajes | B25: Casi todas las variables son % de empresas que respondieron la encuesta en ese trimestre (no son montos de crédito).
A26: Índices de difusión | B26: Escala 0-100. Arriba de 50 = las empresas ven condiciones mejores (más baratas) que el trimestre anterior; abajo de 50 = peores.
A27: pp | B27: Puntos porcentuales: diferencia entre dos porcentajes.
A28: ¿Acumulado? | B28: No. Cada trimestre mide solo lo que pasó en ese trimestre. El IV trimestre no es el acumulado del año; el dato anual es el promedio de los trimestres.

Sheet Series
A1: Encuesta Trimestral de Evaluación Coyuntural del Mercado Crediticio (Banxico) — diseño muestral vigente, IV-2020 a III-2026
A2: Cifras en % de empresas, salvo tasas (%) e índices de difusión (0-100). Datos del trimestre, no acumulados. III-2026 se publica el 19-nov-2026.
A4: Trimestre | B4: Año | C4: Trim. | D4: Fase de política | E4: Índice | F4: Tasa objetivo Banxico fin de trimestre (%) | G4: TIIE 28 días fin de trimestre (%) — pendiente SIE | H4: Usaron nuevo crédito bancario | I4: Promedio móvil 4T nuevo crédito | J4: No solicitaron crédito | K4: Con crédito bancario al inicio — total | L4: Con crédito — hasta 100 empl. | M4: Con crédito — más de 100 empl. | N4: Brecha con crédito por tamaño (pp) | O4: Nuevo crédito — hasta 100 empl. | P4: Nuevo crédito — más de 100 empl. | Q4: Brecha nuevo crédito por tamaño (pp) | R4: Condiciones: ninguna limitante | S4: Limitante menor | T4: Limitante mayor | U4: Fuente: proveedores | V4: Fuente: banca comercial | W4: Banca comercial — hasta 100 empl. | X4: Banca comercial — más de 100 empl. | Y4: Fuente: grupo corporativo | Z4: Solicitaron, en proceso | AA4: Solicitaron y rechazado | AB4: Rechazado — hasta 100 empl. (pendiente) | AC4: Rechazado — más de 100 empl. (pendiente) | AD4: Rechazaron por caro | AE4: Tasa de rechazo (rechazado / (rechazado + nuevo)) | AF4: Tasa de rechazo — hasta 100 empl. | AG4: Tasa de rechazo — más de 100 empl. | AH4: ID costo: tasas de interés | AI4: ID tasas — hasta 100 empl. | AJ4: ID tasas — más de 100 empl. | AK4: ID costo: comisiones | AL4: Esperan pedir crédito bancario próx. trimestre | AM4: Problema más apremiante: ventas | AN4: Problema: acceso al financiamiento | AO4: Limitante: tasas de interés (% de quienes no usaron) | AP4: Limitante: situación económica general (% de quienes no usaron) | AQ4: Empresas que respondieron | AR4: Nota del renglón
A5: IV-20 | B5: 2020 | C5: 4 | D5: 1 Pre-alzas | E5: 1 | F5: 4.25 | H5: 13.6 | J5: 84.2 | K5: 39.7 | L5: 38.7 | M5: 46.9 | N5: =IF(OR(L5="",M5=""),"",ROUND(M5-L5,1)) -> 8.2 | Q5: =IF(OR(O5="",P5=""),"",ROUND(P5-O5,1)) | R5: 47.3 | S5: 34 | T5: 18.7 | AE5: =IF(OR(AA5="",H5=""),"",AA5/(AA5+H5)) | AF5: =IF(OR(AB5="",O5=""),"",AB5/(AB5+O5)) | AG5: =IF(OR(AC5="",P5=""),"",AC5/(AC5+P5))
A6: I-21 | B6: 2021 | C6: 1 | D6: 1 Pre-alzas | E6: 2 | F6: 4 | H6: 15.5 | J6: 78.7 | K6: 39.1 | L6: 37.5 | M6: 51.9 | N6: =IF(OR(L6="",M6=""),"",ROUND(M6-L6,1)) -> 14.4 | Q6: =IF(OR(O6="",P6=""),"",ROUND(P6-O6,1)) | R6: 51.6 | S6: 27.8 | T6: 20.6 | AE6: =IF(OR(AA6="",H6=""),"",AA6/(AA6+H6)) | AF6: =IF(OR(AB6="",O6=""),"",AB6/(AB6+O6)) | AG6: =IF(OR(AC6="",P6=""),"",AC6/(AC6+P6))
A7: II-21 | B7: 2021 | C7: 2 | D7: 2 Alzas | E7: 3 | F7: 4.25 | H7: 11 | J7: 81.6 | K7: 36.6 | L7: 35 | M7: 48.6 | N7: =IF(OR(L7="",M7=""),"",ROUND(M7-L7,1)) -> 13.6 | Q7: =IF(OR(O7="",P7=""),"",ROUND(P7-O7,1)) | R7: 59.5 | S7: 26.6 | T7: 13.9 | AE7: =IF(OR(AA7="",H7=""),"",AA7/(AA7+H7)) | AF7: =IF(OR(AB7="",O7=""),"",AB7/(AB7+O7)) | AG7: =IF(OR(AC7="",P7=""),"",AC7/(AC7+P7))
A8: III-21 | B8: 2021 | C8: 3 | D8: 2 Alzas | E8: 4 | F8: 4.75 | H8: 11.5 | I8: =IF(H8="","",AVERAGE(H5:H8)) -> 12.9 | J8: 81.7 | K8: 37.5 | L8: 35.6 | M8: 52.1 | N8: =IF(OR(L8="",M8=""),"",ROUND(M8-L8,1)) -> 16.5 | Q8: =IF(OR(O8="",P8=""),"",ROUND(P8-O8,1)) | R8: 51 | S8: 26.7 | T8: 22.3 | AE8: =IF(OR(AA8="",H8=""),"",AA8/(AA8+H8)) | AF8: =IF(OR(AB8="",O8=""),"",AB8/(AB8+O8)) | AG8: =IF(OR(AC8="",P8=""),"",AC8/(AC8+P8))
A9: IV-21 | B9: 2021 | C9: 4 | D9: 2 Alzas | E9: 5 | F9: 5.5 | H9: 9 | I9: =IF(H9="","",AVERAGE(H6:H9)) -> 11.75 | J9: 86.3 | K9: 37.5 | L9: 35.3 | M9: 54.4 | N9: =IF(OR(L9="",M9=""),"",ROUND(M9-L9,1)) -> 19.1 | Q9: =IF(OR(O9="",P9=""),"",ROUND(P9-O9,1)) | R9: 49.8 | S9: 31.9 | T9: 18.2 | AE9: =IF(OR(AA9="",H9=""),"",AA9/(AA9+H9)) | AF9: =IF(OR(AB9="",O9=""),"",AB9/(AB9+O9)) | AG9: =IF(OR(AC9="",P9=""),"",AC9/(AC9+P9))
A10: I-22 | B10: 2022 | C10: 1 | D10: 2 Alzas | E10: 6 | F10: 6.5 | H10: 15.2 | I10: =IF(H10="","",AVERAGE(H7:H10)) -> 11.675 | J10: 79.1 | K10: 41.9 | L10: 41.1 | M10: 47.8 | N10: =IF(OR(L10="",M10=""),"",ROUND(M10-L10,1)) -> 6.7 | Q10: =IF(OR(O10="",P10=""),"",ROUND(P10-O10,1)) | R10: 51.2 | S10: 30.9 | T10: 17.9 | AE10: =IF(OR(AA10="",H10=""),"",AA10/(AA10+H10)) | AF10: =IF(OR(AB10="",O10=""),"",AB10/(AB10+O10)) | AG10: =IF(OR(AC10="",P10=""),"",AC10/(AC10+P10))
A11: II-22 | B11: 2022 | C11: 2 | D11: 2 Alzas | E11: 7 | F11: 7.75 | H11: 15.9 | I11: =IF(H11="","",AVERAGE(H8:H11)) -> 12.9 | J11: 79.7 | K11: 40.2 | L11: 38.7 | M11: 51.8 | N11: =IF(OR(L11="",M11=""),"",ROUND(M11-L11,1)) -> 13.1 | Q11: =IF(OR(O11="",P11=""),"",ROUND(P11-O11,1)) | R11: 49.6 | S11: 29.1 | T11: 21.3 | AE11: =IF(OR(AA11="",H11=""),"",AA11/(AA11+H11)) | AF11: =IF(OR(AB11="",O11=""),"",AB11/(AB11+O11)) | AG11: =IF(OR(AC11="",P11=""),"",AC11/(AC11+P11))
A12: III-22 | B12: 2022 | C12: 3 | D12: 2 Alzas | E12: 8 | F12: 9.25 | H12: 16.5 | I12: =IF(H12="","",AVERAGE(H9:H12)) -> 14.15 | J12: 77.7 | K12: 37.9 | L12: 37 | M12: 45.1 | N12: =IF(OR(L12="",M12=""),"",ROUND(M12-L12,1)) -> 8.1 | Q12: =IF(OR(O12="",P12=""),"",ROUND(P12-O12,1)) | R12: 55.2 | S12: 22.5 | T12: 22.3 | U12: 58.4 | V12: 28.9 | Y12: 8.3 | Z12: 3.3 | AA12: 1.4 | AD12: 1.1 | AE12: =IF(OR(AA12="",H12=""),"",AA12/(AA12+H12)) -> 0.078212291 | AF12: =IF(OR(AB12="",O12=""),"",AB12/(AB12+O12)) | AG12: =IF(OR(AC12="",P12=""),"",AC12/(AC12+P12)) | AH12: 23.8 | AK12: 36.4 | AL12: 22 | AM12: 37 | AN12: 2.6 | AO12: 47 | AP12: 47.6
A13: IV-22 | B13: 2022 | C13: 4 | D13: 2 Alzas | E13: 9 | F13: 10.5 | H13: 13.8 | I13: =IF(H13="","",AVERAGE(H10:H13)) -> 15.35 | J13: 79.3 | K13: 37.1 | L13: 36.9 | M13: 38.9 | N13: =IF(OR(L13="",M13=""),"",ROUND(M13-L13,1)) -> 2 | O13: 13 | P13: 20.5 | Q13: =IF(OR(O13="",P13=""),"",ROUND(P13-O13,1)) -> 7.5 | R13: 61.3 | S13: 23.4 | T13: 15.3 | U13: 60.8 | V13: 28.2 | Y13: 9.7 | Z13: 3.1 | AA13: 3.5 | AD13: 0.3 | AE13: =IF(OR(AA13="",H13=""),"",AA13/(AA13+H13)) -> 0.20231214 | AF13: =IF(OR(AB13="",O13=""),"",AB13/(AB13+O13)) | AG13: =IF(OR(AC13="",P13=""),"",AC13/(AC13+P13)) | AH13: 23.7 | AK13: 35.2 | AL13: 20.3 | AM13: 31.5 | AN13: 1.6 | AO13: 48 | AP13: 47.9 | AQ13: 630
A14: I-23 | B14: 2023 | C14: 1 | D14: 2 Alzas | E14: 10 | F14: 11.25 | H14: 15.9 | I14: =IF(H14="","",AVERAGE(H11:H14)) -> 15.525 | J14: 80 | K14: 36.8 | L14: 35.7 | M14: 44.8 | N14: =IF(OR(L14="",M14=""),"",ROUND(M14-L14,1)) -> 9.1 | Q14: =IF(OR(O14="",P14=""),"",ROUND(P14-O14,1)) | R14: 57.7 | S14: 25.4 | T14: 16.9 | U14: 61.2 | V14: 26.5 | Y14: 9.6 | Z14: 1.7 | AA14: 2 | AD14: 0.4 | AE14: =IF(OR(AA14="",H14=""),"",AA14/(AA14+H14)) -> 0.11173184 | AF14: =IF(OR(AB14="",O14=""),"",AB14/(AB14+O14)) | AG14: =IF(OR(AC14="",P14=""),"",AC14/(AC14+P14)) | AH14: 28.9 | AK14: 32.8 | AL14: 21.5 | AM14: 37.2 | AN14: 1.8 | AO14: 55.4 | AP14: 48.7
A15: II-23 | B15: 2023 | C15: 2 | D15: 3 Meseta 11.25% | E15: 11 | F15: 11.25 | H15: 14.8 | I15: =IF(H15="","",AVERAGE(H12:H15)) -> 15.25 | J15: 81.6 | K15: 37.4 | L15: 36.6 | M15: 43.4 | N15: =IF(OR(L15="",M15=""),"",ROUND(M15-L15,1)) -> 6.8 | O15: 14 | P15: 21.6 | Q15: =IF(OR(O15="",P15=""),"",ROUND(P15-O15,1)) -> 7.6 | R15: 57.2 | S15: 25.9 | T15: 16.9 | U15: 59.4 | V15: 28.9 | Y15: 10.9 | Z15: 2.2 | AA15: 0.6 | AD15: 0.9 | AE15: =IF(OR(AA15="",H15=""),"",AA15/(AA15+H15)) -> 0.038961039 | AF15: =IF(OR(AB15="",O15=""),"",AB15/(AB15+O15)) | AG15: =IF(OR(AC15="",P15=""),"",AC15/(AC15+P15)) | AH15: 27.6 | AK15: 37.3 | AL15: 19.4 | AM15: 32.8 | AN15: 0.8 | AO15: 50.8 | AP15: 47.8 | AQ15: 638
A16: III-23 | B16: 2023 | C16: 3 | D16: 3 Meseta 11.25% | E16: 12 | F16: 11.25 | H16: 15.2 | I16: =IF(H16="","",AVERAGE(H13:H16)) -> 14.925 | J16: 80.6 | K16: 36.3 | L16: 35.5 | M16: 42.4 | N16: =IF(OR(L16="",M16=""),"",ROUND(M16-L16,1)) -> 6.9 | Q16: =IF(OR(O16="",P16=""),"",ROUND(P16-O16,1)) | R16: 59.4 | S16: 22.2 | T16: 18.4 | U16: 58.1 | V16: 29.3 | Y16: 13.3 | Z16: 2.8 | AA16: 1.3 | AD16: 0.1 | AE16: =IF(OR(AA16="",H16=""),"",AA16/(AA16+H16)) -> 0.078787879 | AF16: =IF(OR(AB16="",O16=""),"",AB16/(AB16+O16)) | AG16: =IF(OR(AC16="",P16=""),"",AC16/(AC16+P16)) | AH16: 38.9 | AK16: 42 | AL16: 22.3 | AM16: 33.5 | AN16: 2 | AO16: 51.8 | AP16: 48.9
A17: IV-23 | B17: 2023 | C17: 4 | D17: 3 Meseta 11.25% | E17: 13 | F17: 11.25 | H17: 15.6 | I17: =IF(H17="","",AVERAGE(H14:H17)) -> 15.375 | J17: 81.8 | K17: 40.6 | L17: 40.1 | M17: 44.3 | N17: =IF(OR(L17="",M17=""),"",ROUND(M17-L17,1)) -> 4.2 | O17: 15.3 | P17: 18.6 | Q17: =IF(OR(O17="",P17=""),"",ROUND(P17-O17,1)) -> 3.3 | R17: 56.1 | S17: 29.1 | T17: 14.8 | U17: 64.9 | V17: 32.3 | Y17: 14.8 | Z17: 1.4 | AA17: 1 | AD17: 0.2 | AE17: =IF(OR(AA17="",H17=""),"",AA17/(AA17+H17)) -> 0.060240964 | AF17: =IF(OR(AB17="",O17=""),"",AB17/(AB17+O17)) | AG17: =IF(OR(AC17="",P17=""),"",AC17/(AC17+P17)) | AH17: 28.7 | AK17: 28.2 | AL17: 25.2 | AM17: 29.4 | AN17: 1.6 | AO17: 52.5 | AP17: 49 | AQ17: 644
A18: I-24 | B18: 2024 | C18: 1 | D18: 4 Recortes | E18: 14 | F18: 11 | H18: 16.7 | I18: =IF(H18="","",AVERAGE(H15:H18)) -> 15.575 | J18: 78.9 | K18: 39.5 | L18: 38.6 | M18: 46.5 | N18: =IF(OR(L18="",M18=""),"",ROUND(M18-L18,1)) -> 7.9 | O18: 16.3 | P18: 20.2 | Q18: =IF(OR(O18="",P18=""),"",ROUND(P18-O18,1)) -> 3.9 | R18: 56.6 | S18: 24.1 | T18: 19.3 | U18: 64.4 | V18: 30.5 | Y18: 10.3 | Z18: 2.6 | AA18: 1.6 | AD18: 0.2 | AE18: =IF(OR(AA18="",H18=""),"",AA18/(AA18+H18)) -> 0.087431694 | AF18: =IF(OR(AB18="",O18=""),"",AB18/(AB18+O18)) | AG18: =IF(OR(AC18="",P18=""),"",AC18/(AC18+P18)) | AH18: 26.8 | AK18: 25.8 | AL18: 23.1 | AM18: 37.6 | AN18: 2 | AO18: 53.5 | AP18: 47.7 | AR18: Nuevo crédito por tamaño tomado de la cobertura de prensa del comunicado I-2024 (ver Fuentes).
A19: II-24 | B19: 2024 | C19: 2 | D19: 4 Recortes | E19: 15 | F19: 11 | H19: 12.5 | I19: =IF(H19="","",AVERAGE(H16:H19)) -> 15 | J19: 83.5 | K19: 40.1 | L19: 39.3 | M19: 46.2 | N19: =IF(OR(L19="",M19=""),"",ROUND(M19-L19,1)) -> 6.9 | O19: 11.2 | P19: 22.2 | Q19: =IF(OR(O19="",P19=""),"",ROUND(P19-O19,1)) -> 11 | R19: 58.1 | S19: 24.1 | T19: 17.8 | U19: 62.6 | V19: 27.7 | Y19: 12.1 | Z19: 3.3 | AA19: 0.5 | AD19: 0.2 | AE19: =IF(OR(AA19="",H19=""),"",AA19/(AA19+H19)) -> 0.038461538 | AF19: =IF(OR(AB19="",O19=""),"",AB19/(AB19+O19)) | AG19: =IF(OR(AC19="",P19=""),"",AC19/(AC19+P19)) | AH19: 28 | AK19: 34.7 | AL19: 24.2 | AM19: 40.5 | AN19: 2.2 | AO19: 50.1 | AP19: 49.3 | AQ19: 648
A20: III-24 | B20: 2024 | C20: 3 | D20: 4 Recortes | E20: 16 | F20: 10.5 | H20: 15.2 | I20: =IF(H20="","",AVERAGE(H17:H20)) -> 15 | J20: 79.5 | K20: 39.9 | L20: 38.9 | M20: 47.5 | N20: =IF(OR(L20="",M20=""),"",ROUND(M20-L20,1)) -> 8.6 | Q20: =IF(OR(O20="",P20=""),"",ROUND(P20-O20,1)) | R20: 54.5 | S20: 26.8 | T20: 18.7 | U20: 58.4 | V20: 28 | Y20: 12.3 | Z20: 3.1 | AA20: 0.9 | AD20: 1.4 | AE20: =IF(OR(AA20="",H20=""),"",AA20/(AA20+H20)) -> 0.055900621 | AF20: =IF(OR(AB20="",O20=""),"",AB20/(AB20+O20)) | AG20: =IF(OR(AC20="",P20=""),"",AC20/(AC20+P20)) | AH20: 41.1 | AK20: 40.5 | AL20: 25.7 | AM20: 37.2 | AN20: 1.6 | AO20: 54.6 | AP20: 58.1
A21: IV-24 | B21: 2024 | C21: 4 | D21: 4 Recortes | E21: 17 | F21: 10 | H21: 12.1 | I21: =IF(H21="","",AVERAGE(H18:H21)) -> 14.125 | J21: 84.7 | K21: 36.3 | L21: 34.8 | M21: 48 | N21: =IF(OR(L21="",M21=""),"",ROUND(M21-L21,1)) -> 13.2 | O21: 10.9 | P21: 21.4 | Q21: =IF(OR(O21="",P21=""),"",ROUND(P21-O21,1)) -> 10.5 | R21: 55.4 | S21: 25.7 | T21: 18.8 | U21: 60 | V21: 28 | Y21: 16.2 | Z21: 1.2 | AA21: 1.3 | AD21: 0.8 | AE21: =IF(OR(AA21="",H21=""),"",AA21/(AA21+H21)) -> 0.097014925 | AF21: =IF(OR(AB21="",O21=""),"",AB21/(AB21+O21)) | AG21: =IF(OR(AC21="",P21=""),"",AC21/(AC21+P21)) | AH21: 33.7 | AK21: 34.3 | AL21: 23.1 | AM21: 40.9 | AN21: 1.9 | AO21: 54.1 | AP21: 50.8 | AQ21: 664
A22: I-25 | B22: 2025 | C22: 1 | D22: 4 Recortes | E22: 18 | F22: 9 | H22: 13.3 | I22: =IF(H22="","",AVERAGE(H19:H22)) -> 13.275 | J22: 82.2 | K22: 37.4 | L22: 36.3 | M22: 45.9 | N22: =IF(OR(L22="",M22=""),"",ROUND(M22-L22,1)) -> 9.6 | Q22: =IF(OR(O22="",P22=""),"",ROUND(P22-O22,1)) | R22: 55.6 | S22: 27.3 | T22: 17.1 | U22: 62.1 | V22: 27.3 | Y22: 12.9 | Z22: 2.6 | AA22: 1 | AD22: 0.9 | AE22: =IF(OR(AA22="",H22=""),"",AA22/(AA22+H22)) -> 0.06993007 | AF22: =IF(OR(AB22="",O22=""),"",AB22/(AB22+O22)) | AG22: =IF(OR(AC22="",P22=""),"",AC22/(AC22+P22)) | AH22: 39.3 | AK22: 38.2 | AL22: 21.9 | AM22: 37.4 | AN22: 1.1 | AO22: 52.7 | AP22: 54.6
A23: II-25 | B23: 2025 | C23: 2 | D23: 4 Recortes | E23: 19 | F23: 8 | H23: 14.9 | I23: =IF(H23="","",AVERAGE(H20:H23)) -> 13.875 | J23: 82.3 | K23: 35.8 | L23: 34.5 | M23: 46 | N23: =IF(OR(L23="",M23=""),"",ROUND(M23-L23,1)) -> 11.5 | O23: 14.1 | P23: 21.4 | Q23: =IF(OR(O23="",P23=""),"",ROUND(P23-O23,1)) -> 7.3 | R23: 56.5 | S23: 23.8 | T23: 19.7 | U23: 60.6 | V23: 29.9 | Y23: 10.6 | Z23: 1.7 | AA23: 0.8 | AD23: 0.3 | AE23: =IF(OR(AA23="",H23=""),"",AA23/(AA23+H23)) -> 0.050955414 | AF23: =IF(OR(AB23="",O23=""),"",AB23/(AB23+O23)) | AG23: =IF(OR(AC23="",P23=""),"",AC23/(AC23+P23)) | AH23: 46.7 | AK23: 39.2 | AL23: 19.4 | AM23: 47.8 | AN23: 1.1 | AO23: 51.3 | AP23: 55.4 | AQ23: 650
A24: III-25 | B24: 2025 | C24: 3 | D24: 4 Recortes | E24: 20 | F24: 7.5 | H24: 11.5 | I24: =IF(H24="","",AVERAGE(H21:H24)) -> 12.95 | J24: 85.2 | K24: 37.6 | L24: 36.6 | M24: 45.5 | N24: =IF(OR(L24="",M24=""),"",ROUND(M24-L24,1)) -> 8.9 | Q24: =IF(OR(O24="",P24=""),"",ROUND(P24-O24,1)) | R24: 56.3 | S24: 26.7 | T24: 17 | U24: 56.4 | V24: 25.3 | Y24: 12.9 | Z24: 1.7 | AA24: 1.3 | AD24: 0.3 | AE24: =IF(OR(AA24="",H24=""),"",AA24/(AA24+H24)) -> 0.1015625 | AF24: =IF(OR(AB24="",O24=""),"",AB24/(AB24+O24)) | AG24: =IF(OR(AC24="",P24=""),"",AC24/(AC24+P24)) | AH24: 49 | AK24: 41.8 | AL24: 21.3 | AM24: 41.5 | AN24: 2.2 | AO24: 52.6 | AP24: 58.8
A25: IV-25 | B25: 2025 | C25: 4 | D25: 4 Recortes | E25: 21 | F25: 7 | H25: 15.3 | I25: =IF(H25="","",AVERAGE(H22:H25)) -> 13.75 | J25: 81.5 | K25: 38.4 | L25: 37.1 | M25: 48 | N25: =IF(OR(L25="",M25=""),"",ROUND(M25-L25,1)) -> 10.9 | O25: 14.5 | P25: 22.2 | Q25: =IF(OR(O25="",P25=""),"",ROUND(P25-O25,1)) -> 7.7 | R25: 50.8 | S25: 29.1 | T25: 20.1 | U25: 62.2 | V25: 26.5 | Y25: 11.2 | Z25: 2.4 | AA25: 0.5 | AD25: 0.2 | AE25: =IF(OR(AA25="",H25=""),"",AA25/(AA25+H25)) -> 0.03164557 | AF25: =IF(OR(AB25="",O25=""),"",AB25/(AB25+O25)) | AG25: =IF(OR(AC25="",P25=""),"",AC25/(AC25+P25)) | AH25: 47.6 | AK25: 40.9 | AL25: 19.3 | AM25: 42.5 | AN25: 2 | AO25: 57.3 | AP25: 57.9 | AQ25: 647
A26: I-26 | B26: 2026 | C26: 1 | D26: 4 Recortes | E26: 22 | F26: 6.75 | H26: 13.1 | I26: =IF(H26="","",AVERAGE(H23:H26)) -> 13.7 | J26: 79.2 | K26: 37 | L26: 35.8 | M26: 46.5 | N26: =IF(OR(L26="",M26=""),"",ROUND(M26-L26,1)) -> 10.7 | O26: 12.1 | P26: 20.4 | Q26: =IF(OR(O26="",P26=""),"",ROUND(P26-O26,1)) -> 8.3 | R26: 56.1 | S26: 23.5 | T26: 20.4 | U26: 64.3 | V26: 25 | Y26: 12.1 | Z26: 3.9 | AA26: 3.8 | AD26: 0 | AE26: =IF(OR(AA26="",H26=""),"",AA26/(AA26+H26)) -> 0.22485207 | AF26: =IF(OR(AB26="",O26=""),"",AB26/(AB26+O26)) | AG26: =IF(OR(AC26="",P26=""),"",AC26/(AC26+P26)) | AH26: 44.9 | AK26: 32.7 | AL26: 18.7 | AM26: 42 | AN26: 2.1 | AO26: 48.5 | AP26: 60.7 | AR26: Nuevo crédito por tamaño: Yahoo Noticias con datos del comunicado I-2026 (ver Fuentes).
A27: II-26 | B27: 2026 | C27: 2 | D27: 4 Recortes | E27: 23 | F27: 6.5 | H27: 11.2 | I27: =IF(H27="","",AVERAGE(H24:H27)) -> 12.775 | J27: 82.1 | K27: 37.3 | L27: 35.7 | M27: 49.7 | N27: =IF(OR(L27="",M27=""),"",ROUND(M27-L27,1)) -> 14 | O27: 9.9 | P27: 21.6 | Q27: =IF(OR(O27="",P27=""),"",ROUND(P27-O27,1)) -> 11.7 | R27: 50.9 | S27: 30.7 | T27: 18.5 | U27: 60.9 | V27: 24.5 | W27: 22.7 | X27: 38.4 | Y27: 11.2 | Z27: 3 | AA27: 3.6 | AD27: 0.1 | AE27: =IF(OR(AA27="",H27=""),"",AA27/(AA27+H27)) -> 0.24324324 | AF27: =IF(OR(AB27="",O27=""),"",AB27/(AB27+O27)) | AG27: =IF(OR(AC27="",P27=""),"",AC27/(AC27+P27)) | AH27: 39.4 | AI27: 35.3 | AJ27: 53.7 | AK27: 34.9 | AL27: 20.3 | AM27: 44.6 | AN27: 1.2 | AO27: 55.6 | AP27: 62.6 | AQ27: 653 | AR27: ID tasas y banca comercial por tamaño: texto del comunicado II-2026.
A28: III-26 | B28: 2026 | C28: 3 | D28: 5 Pausa 6.50% | E28: 24 | F28: 6.5 | I28: =IF(H28="","",AVERAGE(H25:H28)) | N28: =IF(OR(L28="",M28=""),"",ROUND(M28-L28,1)) | Q28: =IF(OR(O28="",P28=""),"",ROUND(P28-O28,1)) | AE28: =IF(OR(AA28="",H28=""),"",AA28/(AA28+H28)) | AF28: =IF(OR(AB28="",O28=""),"",AB28/(AB28+O28)) | AG28: =IF(OR(AC28="",P28=""),"",AC28/(AC28+P28)) | AR28: Encuesta julio-septiembre 2026: Banxico la publica el 19-nov-2026. Solo se conoce la tasa objetivo (6.50%, decisión del 24-sep-2026).
A30: Amarillo = pendiente. TIIE: descargar del SIE de Banxico (serie SF43783, TIIE a 28 días) el último día hábil de cada trimestre. Rechazo por tamaño: cuadro 2 de cada comunicado / SIE CF910. III-2026: comunicado del 19-nov-2026.
A31: Nuevo crédito por tamaño: se capturó de los comunicados II y IV de cada año y de la cobertura de prensa de I-24 e I-26; los demás trimestres quedan vacíos hasta descargarlos del SIE.
A32: Los porcentajes son del trimestre (no acumulados). La tasa de rechazo usa como aprobadas a las empresas que usaron crédito nuevo.
A51: Fuente: Banxico, comunicados 'Evolución trimestral del financiamiento a las empresas', diseño vigente, IV-2020 a II-2026. Puntos = trimestre; línea azul = promedio móvil de 4 trimestres; línea punteada = tendencia lineal. Datos: columnas H e I de esta hoja.

Sheet Serie completa 2020-2026
A1: Serie completa 2020-2026: los 27 trimestres, de I-2020 a III-2026
A2: I-III 2020 = muestra anterior (Banxico no recalculó esos trimestres con el diseño vigente). IV-2020 en adelante = diseño vigente. % de empresas del trimestre.
A4: Trimestre | B4: Año | C4: Trim. | D4: Índice | E4: Muestra | F4: Tasa objetivo fin de trimestre (%) | G4: TIIE 28 días (%) — pendiente | H4: Usaron nuevo crédito bancario (%) | I4: Con crédito al inicio (%) | J4: ID tasas de interés (índice)* | K4: Sin limitante (%) | L4: Nuevo crédito — diseño vigente (para gráfica) | M4: Nuevo crédito — muestra anterior (referencia) | N4: Tendencia lineal IV-20 a II-26 | O4: Tendencia lineal desde I-23
A5: I-20 | B5: 2020 | C5: 1 | D5: 1 | E5: Anterior (≥450 emp.) | F5: 6.5 | H5: ='Muestra anterior'!B5 -> 24.2 | I5: ='Muestra anterior'!E5 -> 47.6 | J5: ='Muestra anterior'!H5 -> 61.1 | K5: ='Muestra anterior'!I5 -> 54.5 | M5: ='Muestra anterior'!B5 -> 24.2
A6: II-20 | B6: 2020 | C6: 2 | D6: 2 | E6: Anterior (≥450 emp.) | F6: 5 | H6: ='Muestra anterior'!B6 -> 21.6 | I6: ='Muestra anterior'!E6 -> 47.5 | J6: ='Muestra anterior'!H6 -> 38.5 | K6: ='Muestra anterior'!I6 -> 48.1 | M6: ='Muestra anterior'!B6 -> 21.6
A7: III-20 | B7: 2020 | C7: 3 | D7: 3 | E7: Anterior (≥450 emp.) | F7: 4.25 | H7: ='Muestra anterior'!B7 -> 19 | I7: ='Muestra anterior'!E7 -> 46.9 | J7: ='Muestra anterior'!H7 -> 50.8 | K7: ='Muestra anterior'!I7 -> 48.5 | M7: ='Muestra anterior'!B7 -> 19
A8: IV-20 | B8: 2020 | C8: 4 | D8: 4 | E8: Vigente | F8: =Series!F5 -> 4.25 | G8: =IF(Series!G5="","",Series!G5) | H8: =Series!H5 -> 13.6 | I8: =Series!K5 -> 39.7 | J8: ='Muestra anterior'!H8 -> 45.1 | K8: =Series!R5 -> 47.3 | L8: =Series!H5 -> 13.6 | M8: ='Muestra anterior'!B8 -> 16.8 | N8: =INTERCEPT($L$5:$L$30,$D$5:$D$30)+SLOPE($L$5:$L$30,$D$5:$D$30)*D8 -> 13.96413
A9: I-21 | B9: 2021 | C9: 1 | D9: 5 | E9: Vigente | F9: =Series!F6 -> 4 | G9: =IF(Series!G6="","",Series!G6) | H9: =Series!H6 -> 15.5 | I9: =Series!K6 -> 39.1 | J9: ='Muestra anterior'!H9 -> 52.8 | K9: =Series!R6 -> 51.6 | L9: =Series!H6 -> 15.5 | M9: ='Muestra anterior'!B9 -> 20.8 | N9: =INTERCEPT($L$5:$L$30,$D$5:$D$30)+SLOPE($L$5:$L$30,$D$5:$D$30)*D9 -> 13.956719
A10: II-21 | B10: 2021 | C10: 2 | D10: 6 | E10: Vigente | F10: =Series!F7 -> 4.25 | G10: =IF(Series!G7="","",Series!G7) | H10: =Series!H7 -> 11 | I10: =Series!K7 -> 36.6 | J10: ='Muestra anterior'!H10 -> 32.6 | K10: =Series!R7 -> 59.5 | L10: =Series!H7 -> 11 | M10: ='Muestra anterior'!B10 -> 17.4 | N10: =INTERCEPT($L$5:$L$30,$D$5:$D$30)+SLOPE($L$5:$L$30,$D$5:$D$30)*D10 -> 13.949308
A11: III-21 | B11: 2021 | C11: 3 | D11: 7 | E11: Vigente | F11: =Series!F8 -> 4.75 | G11: =IF(Series!G8="","",Series!G8) | H11: =Series!H8 -> 11.5 | I11: =Series!K8 -> 37.5 | J11: ='Muestra anterior'!H11 -> 33.8 | K11: =Series!R8 -> 51 | L11: =Series!H8 -> 11.5 | M11: ='Muestra anterior'!B11 -> 19.3 | N11: =INTERCEPT($L$5:$L$30,$D$5:$D$30)+SLOPE($L$5:$L$30,$D$5:$D$30)*D11 -> 13.941897
A12: IV-21 | B12: 2021 | C12: 4 | D12: 8 | E12: Vigente | F12: =Series!F9 -> 5.5 | G12: =IF(Series!G9="","",Series!G9) | H12: =Series!H9 -> 9 | I12: =Series!K9 -> 37.5 | J12: ='Muestra anterior'!H12 -> 27.7 | K12: =Series!R9 -> 49.8 | L12: =Series!H9 -> 9 | M12: ='Muestra anterior'!B12 -> 17.8 | N12: =INTERCEPT($L$5:$L$30,$D$5:$D$30)+SLOPE($L$5:$L$30,$D$5:$D$30)*D12 -> 13.934486
A13: I-22 | B13: 2022 | C13: 1 | D13: 9 | E13: Vigente | F13: =Series!F10 -> 6.5 | G13: =IF(Series!G10="","",Series!G10) | H13: =Series!H10 -> 15.2 | I13: =Series!K10 -> 41.9 | J13: ='Muestra anterior'!H13 -> 23.6 | K13: =Series!R10 -> 51.2 | L13: =Series!H10 -> 15.2 | M13: ='Muestra anterior'!B13 -> 19.5 | N13: =INTERCEPT($L$5:$L$30,$D$5:$D$30)+SLOPE($L$5:$L$30,$D$5:$D$30)*D13 -> 13.927075
A14: II-22 | B14: 2022 | C14: 2 | D14: 10 | E14: Vigente | F14: =Series!F11 -> 7.75 | G14: =IF(Series!G11="","",Series!G11) | H14: =Series!H11 -> 15.9 | I14: =Series!K11 -> 40.2 | J14: ='Muestra anterior'!H14 -> 19.2 | K14: =Series!R11 -> 49.6 | L14: =Series!H11 -> 15.9 | M14: ='Muestra anterior'!B14 -> 21 | N14: =INTERCEPT($L$5:$L$30,$D$5:$D$30)+SLOPE($L$5:$L$30,$D$5:$D$30)*D14 -> 13.919664
A15: III-22 | B15: 2022 | C15: 3 | D15: 11 | E15: Vigente | F15: =Series!F12 -> 9.25 | G15: =IF(Series!G12="","",Series!G12) | H15: =Series!H12 -> 16.5 | I15: =Series!K12 -> 37.9 | J15: =Series!AH12 -> 23.8 | K15: =Series!R12 -> 55.2 | L15: =Series!H12 -> 16.5 | N15: =INTERCEPT($L$5:$L$30,$D$5:$D$30)+SLOPE($L$5:$L$30,$D$5:$D$30)*D15 -> 13.912253
A16: IV-22 | B16: 2022 | C16: 4 | D16: 12 | E16: Vigente | F16: =Series!F13 -> 10.5 | G16: =IF(Series!G13="","",Series!G13) | H16: =Series!H13 -> 13.8 | I16: =Series!K13 -> 37.1 | J16: =Series!AH13 -> 23.7 | K16: =Series!R13 -> 61.3 | L16: =Series!H13 -> 13.8 | N16: =INTERCEPT($L$5:$L$30,$D$5:$D$30)+SLOPE($L$5:$L$30,$D$5:$D$30)*D16 -> 13.904842
A17: I-23 | B17: 2023 | C17: 1 | D17: 13 | E17: Vigente | F17: =Series!F14 -> 11.25 | G17: =IF(Series!G14="","",Series!G14) | H17: =Series!H14 -> 15.9 | I17: =Series!K14 -> 36.8 | J17: =Series!AH14 -> 28.9 | K17: =Series!R14 -> 57.7 | L17: =Series!H14 -> 15.9 | N17: =INTERCEPT($L$5:$L$30,$D$5:$D$30)+SLOPE($L$5:$L$30,$D$5:$D$30)*D17 -> 13.897431 | O17: =INTERCEPT($L$17:$L$30,$D$17:$D$30)+SLOPE($L$17:$L$30,$D$17:$D$30)*D17 -> 15.768571
A18: II-23 | B18: 2023 | C18: 2 | D18: 14 | E18: Vigente | F18: =Series!F15 -> 11.25 | G18: =IF(Series!G15="","",Series!G15) | H18: =Series!H15 -> 14.8 | I18: =Series!K15 -> 37.4 | J18: =Series!AH15 -> 27.6 | K18: =Series!R15 -> 57.2 | L18: =Series!H15 -> 14.8 | N18: =INTERCEPT($L$5:$L$30,$D$5:$D$30)+SLOPE($L$5:$L$30,$D$5:$D$30)*D18 -> 13.89002 | O18: =INTERCEPT($L$17:$L$30,$D$17:$D$30)+SLOPE($L$17:$L$30,$D$17:$D$30)*D18 -> 15.510769
A19: III-23 | B19: 2023 | C19: 3 | D19: 15 | E19: Vigente | F19: =Series!F16 -> 11.25 | G19: =IF(Series!G16="","",Series!G16) | H19: =Series!H16 -> 15.2 | I19: =Series!K16 -> 36.3 | J19: =Series!AH16 -> 38.9 | K19: =Series!R16 -> 59.4 | L19: =Series!H16 -> 15.2 | N19: =INTERCEPT($L$5:$L$30,$D$5:$D$30)+SLOPE($L$5:$L$30,$D$5:$D$30)*D19 -> 13.882609 | O19: =INTERCEPT($L$17:$L$30,$D$17:$D$30)+SLOPE($L$17:$L$30,$D$17:$D$30)*D19 -> 15.252967
A20: IV-23 | B20: 2023 | C20: 4 | D20: 16 | E20: Vigente | F20: =Series!F17 -> 11.25 | G20: =IF(Series!G17="","",Series!G17) | H20: =Series!H17 -> 15.6 | I20: =Series!K17 -> 40.6 | J20: =Series!AH17 -> 28.7 | K20: =Series!R17 -> 56.1 | L20: =Series!H17 -> 15.6 | N20: =INTERCEPT($L$5:$L$30,$D$5:$D$30)+SLOPE($L$5:$L$30,$D$5:$D$30)*D20 -> 13.875198 | O20: =INTERCEPT($L$17:$L$30,$D$17:$D$30)+SLOPE($L$17:$L$30,$D$17:$D$30)*D20 -> 14.995165
A21: I-24 | B21: 2024 | C21: 1 | D21: 17 | E21: Vigente | F21: =Series!F18 -> 11 | G21: =IF(Series!G18="","",Series!G18) | H21: =Series!H18 -> 16.7 | I21: =Series!K18 -> 39.5 | J21: =Series!AH18 -> 26.8 | K21: =Series!R18 -> 56.6 | L21: =Series!H18 -> 16.7 | N21: =INTERCEPT($L$5:$L$30,$D$5:$D$30)+SLOPE($L$5:$L$30,$D$5:$D$30)*D21 -> 13.867787 | O21: =INTERCEPT($L$17:$L$30,$D$17:$D$30)+SLOPE($L$17:$L$30,$D$17:$D$30)*D21 -> 14.737363
A22: II-24 | B22: 2024 | C22: 2 | D22: 18 | E22: Vigente | F22: =Series!F19 -> 11 | G22: =IF(Series!G19="","",Series!G19) | H22: =Series!H19 -> 12.5 | I22: =Series!K19 -> 40.1 | J22: =Series!AH19 -> 28 | K22: =Series!R19 -> 58.1 | L22: =Series!H19 -> 12.5 | N22: =INTERCEPT($L$5:$L$30,$D$5:$D$30)+SLOPE($L$5:$L$30,$D$5:$D$30)*D22 -> 13.860375 | O22: =INTERCEPT($L$17:$L$30,$D$17:$D$30)+SLOPE($L$17:$L$30,$D$17:$D$30)*D22 -> 14.47956
A23: III-24 | B23: 2024 | C23: 3 | D23: 19 | E23: Vigente | F23: =Series!F20 -> 10.5 | G23: =IF(Series!G20="","",Series!G20) | H23: =Series!H20 -> 15.2 | I23: =Series!K20 -> 39.9 | J23: =Series!AH20 -> 41.1 | K23: =Series!R20 -> 54.5 | L23: =Series!H20 -> 15.2 | N23: =INTERCEPT($L$5:$L$30,$D$5:$D$30)+SLOPE($L$5:$L$30,$D$5:$D$30)*D23 -> 13.852964 | O23: =INTERCEPT($L$17:$L$30,$D$17:$D$30)+SLOPE($L$17:$L$30,$D$17:$D$30)*D23 -> 14.221758
A24: IV-24 | B24: 2024 | C24: 4 | D24: 20 | E24: Vigente | F24: =Series!F21 -> 10 | G24: =IF(Series!G21="","",Series!G21) | H24: =Series!H21 -> 12.1 | I24: =Series!K21 -> 36.3 | J24: =Series!AH21 -> 33.7 | K24: =Series!R21 -> 55.4 | L24: =Series!H21 -> 12.1 | N24: =INTERCEPT($L$5:$L$30,$D$5:$D$30)+SLOPE($L$5:$L$30,$D$5:$D$30)*D24 -> 13.845553 | O24: =INTERCEPT($L$17:$L$30,$D$17:$D$30)+SLOPE($L$17:$L$30,$D$17:$D$30)*D24 -> 13.963956
A25: I-25 | B25: 2025 | C25: 1 | D25: 21 | E25: Vigente | F25: =Series!F22 -> 9 | G25: =IF(Series!G22="","",Series!G22) | H25: =Series!H22 -> 13.3 | I25: =Series!K22 -> 37.4 | J25: =Series!AH22 -> 39.3 | K25: =Series!R22 -> 55.6 | L25: =Series!H22 -> 13.3 | N25: =INTERCEPT($L$5:$L$30,$D$5:$D$30)+SLOPE($L$5:$L$30,$D$5:$D$30)*D25 -> 13.838142 | O25: =INTERCEPT($L$17:$L$30,$D$17:$D$30)+SLOPE($L$17:$L$30,$D$17:$D$30)*D25 -> 13.706154
A26: II-25 | B26: 2025 | C26: 2 | D26: 22 | E26: Vigente | F26: =Series!F23 -> 8 | G26: =IF(Series!G23="","",Series!G23) | H26: =Series!H23 -> 14.9 | I26: =Series!K23 -> 35.8 | J26: =Series!AH23 -> 46.7 | K26: =Series!R23 -> 56.5 | L26: =Series!H23 -> 14.9 | N26: =INTERCEPT($L$5:$L$30,$D$5:$D$30)+SLOPE($L$5:$L$30,$D$5:$D$30)*D26 -> 13.830731 | O26: =INTERCEPT($L$17:$L$30,$D$17:$D$30)+SLOPE($L$17:$L$30,$D$17:$D$30)*D26 -> 13.448352
A27: III-25 | B27: 2025 | C27: 3 | D27: 23 | E27: Vigente | F27: =Series!F24 -> 7.5 | G27: =IF(Series!G24="","",Series!G24) | H27: =Series!H24 -> 11.5 | I27: =Series!K24 -> 37.6 | J27: =Series!AH24 -> 49 | K27: =Series!R24 -> 56.3 | L27: =Series!H24 -> 11.5 | N27: =INTERCEPT($L$5:$L$30,$D$5:$D$30)+SLOPE($L$5:$L$30,$D$5:$D$30)*D27 -> 13.82332 | O27: =INTERCEPT($L$17:$L$30,$D$17:$D$30)+SLOPE($L$17:$L$30,$D$17:$D$30)*D27 -> 13.190549
A28: IV-25 | B28: 2025 | C28: 4 | D28: 24 | E28: Vigente | F28: =Series!F25 -> 7 | G28: =IF(Series!G25="","",Series!G25) | H28: =Series!H25 -> 15.3 | I28: =Series!K25 -> 38.4 | J28: =Series!AH25 -> 47.6 | K28: =Series!R25 -> 50.8 | L28: =Series!H25 -> 15.3 | N28: =INTERCEPT($L$5:$L$30,$D$5:$D$30)+SLOPE($L$5:$L$30,$D$5:$D$30)*D28 -> 13.815909 | O28: =INTERCEPT($L$17:$L$30,$D$17:$D$30)+SLOPE($L$17:$L$30,$D$17:$D$30)*D28 -> 12.932747
... A30: II-26 | B30: 2026 | C30: 2 | D30: 26 | E30: Vigente | F30: =Series!F27 -> 6.5 | G30: =IF(Series!G27="","",Series!G27) | H30: =Series!H27 -> 11.2 | I30: =Series!K27 -> 37.3 | J30: =Series!AH27 -> 39.4 | K30: =Series!R27 -> 50.9 | L30: =Series!H27 -> 11.2 | N30: =INTERCEPT($L$5:$L$30,$D$5:$D$30)+SLOPE($L$5:$L$30,$D$5:$D$30)*D30 -> 13.801087 | O30: =INTERCEPT($L$17:$L$30,$D$17:$D$30)+SLOPE($L$17:$L$30,$D$17:$D$30)*D30 -> 12.417143
A31: III-26 | B31: 2026 | C31: 3 | D31: 27 | E31: Vigente | F31: =Series!F28 -> 6.5 | G31: =IF(Series!G28="","",Series!G28)
A33: * ID tasas: muestra anterior de I-20 a II-22 (el diseño vigente publica el índice desde III-22). Índice > 50 = crédito más barato; < 50 = más caro.
A34: Columnas N y O: rectas de mínimos cuadrados sobre el diseño vigente. En todo el periodo la tendencia es casi plana (2021 fue bajo); desde I-23 la pendiente es negativa.
M36: Pendiente de la tendencia | N36: IV-20 a II-26 | O36: Desde I-23
M37: pp por trimestre | N37: =SLOPE($L$5:$L$30,$D$5:$D$30) -> -0.0074110672 | O37: =SLOPE($L$17:$L$30,$D$17:$D$30) -> -0.2578022
M38: pp por año | N38: =N37*4 -> -0.029644269 | O38: =O37*4 -> -1.0312088
A57: Fuente: Banxico, comunicados de la Encuesta de Evaluación Coyuntural del Mercado Crediticio: muestra anterior (I-2020 a II-2022) y diseño vigente (IV-2020 a II-2026). Líneas punteadas = tendencia lineal del diseño vigente (todo el periodo y desde I-23). Datos: columnas L a O de esta hoja.
A76: Fuente: Banxico, cuadro 2 de los comunicados; muestra anterior I-2020 a II-2022, diseño vigente III-2022 a II-2026. Datos: columna J de esta hoja.

Sheet Resumen anual
A1: Resumen anual 2020-2026 (promedio simple de los trimestres de cada año)
A2: 2020 se muestra en dos renglones: muestra anterior (los 4 trimestres) y diseño vigente (solo IV-20). 2026 = I y II trimestre; III se publica el 19-nov-2026.
A4: Año | B4: Muestra / trimestres | C4: Trimestres con dato | D4: Usaron nuevo crédito (promedio) | E4: Nuevo crédito, solo IV trimestre (no acumulado) | F4: Con crédito al inicio — total | G4: Con crédito — hasta 100 empl. | H4: Con crédito — más de 100 empl. | I4: Brecha con crédito (pp) | J4: Nuevo crédito — hasta 100 empl. | K4: Nuevo crédito — más de 100 empl. | L4: Brecha nuevo crédito (pp) | M4: Condiciones: ninguna limitante | N4: Limitante mayor | O4: Fuente: banca comercial | P4: ID costo: tasas de interés | Q4: Tasa de rechazo | R4: Tasa objetivo fin de trimestre (%) | S4: TIIE 28 días (%) | T4: Etiqueta para gráfica
A5: 2020 | B5: Muestra anterior (I-IV) | C5: =COUNT('Muestra anterior'!B5:B8) -> 4 | D5: ='Muestra anterior'!B18 -> 20.4 | E5: ='Muestra anterior'!B8 -> 16.8 | F5: ='Muestra anterior'!E18 -> 46.475 | G5: n.d. | H5: n.d. | I5: n.d. | J5: n.d. | K5: n.d. | L5: n.d. | M5: ='Muestra anterior'!I18 -> 50.325 | N5: n.d. | O5: n.d. | P5: ='Muestra anterior'!H18 -> 48.875 | Q5: n.d. | R5: =AVERAGEIFS('Serie completa 2020-2026'!$F$5:$F$31,'Serie completa 2020-2026'!$B$5:$B$31,A5) -> 5 | S5: =IFERROR(AVERAGEIFS('Serie completa 2020-2026'!$G$5:$G$31,'Serie completa 2020-2026'!$B$5:$B$31,A5),"pend.") -> pend. | T5: 2020 ant.
A6: 2020 | B6: Diseño vigente (solo IV) | C6: =COUNTIFS(Series!$B$5:$B$28,$A6,Series!$H$5:$H$28,"<>") -> 1 | D6: =IFERROR(ROUND(AVERAGEIFS(Series!$H$5:$H$28,Series!$B$5:$B$28,$A6),3),"n.d.") -> 13.6 | E6: =IFERROR(INDEX(Series!$H$5:$H$28,MATCH("IV-"&RIGHT($A6,2),Series!$A$5:$A$28,0)),"n.d.") -> 13.6 | F6: =IFERROR(ROUND(AVERAGEIFS(Series!$K$5:$K$28,Series!$B$5:$B$28,$A6),3),"n.d.") -> 39.7 | G6: =IFERROR(ROUND(AVERAGEIFS(Series!$L$5:$L$28,Series!$B$5:$B$28,$A6),3),"n.d.") -> 38.7 | H6: =IFERROR(ROUND(AVERAGEIFS(Series!$M$5:$M$28,Series!$B$5:$B$28,$A6),3),"n.d.") -> 46.9 | I6: =IFERROR(ROUND(AVERAGEIFS(Series!$N$5:$N$28,Series!$B$5:$B$28,$A6),3),"n.d.") -> 8.2 | J6: =IFERROR(ROUND(AVERAGEIFS(Series!$O$5:$O$28,Series!$B$5:$B$28,$A6),3),"n.d.") -> n.d. | K6: =IFERROR(ROUND(AVERAGEIFS(Series!$P$5:$P$28,Series!$B$5:$B$28,$A6),3),"n.d.") -> n.d. | L6: =IFERROR(ROUND(AVERAGEIFS(Series!$Q$5:$Q$28,Series!$B$5:$B$28,$A6),3),"n.d.") -> n.d. | M6: =IFERROR(ROUND(AVERAGEIFS(Series!$R$5:$R$28,Series!$B$5:$B$28,$A6),3),"n.d.") -> 47.3 | N6: =IFERROR(ROUND(AVERAGEIFS(Series!$T$5:$T$28,Series!$B$5:$B$28,$A6),3),"n.d.") -> 18.7 | O6: =IFERROR(ROUND(AVERAGEIFS(Series!$V$5:$V$28,Series!$B$5:$B$28,$A6),3),"n.d.") -> n.d. | P6: =IFERROR(ROUND(AVERAGEIFS(Series!$AH$5:$AH$28,Series!$B$5:$B$28,$A6),3),"n.d.") -> n.d. | Q6: =IFERROR(ROUND(AVERAGEIFS(Series!$AE$5:$AE$28,Series!$B$5:$B$28,$A6),5),"n.d.") -> n.d. | R6: =IFERROR(AVERAGEIFS(Series!$F$5:$F$28,Series!$B$5:$B$28,$A6),"n.d.") -> 4.25 | S6: =IFERROR(AVERAGEIFS(Series!$G$5:$G$28,Series!$B$5:$B$28,$A6),"pend.") -> pend. | T6: 2020 vig. (IV)
A7: 2021 | B7: Diseño vigente | C7: =COUNTIFS(Series!$B$5:$B$28,$A7,Series!$H$5:$H$28,"<>") -> 4 | D7: =IFERROR(ROUND(AVERAGEIFS(Series!$H$5:$H$28,Series!$B$5:$B$28,$A7),3),"n.d.") -> 11.75 | E7: =IFERROR(INDEX(Series!$H$5:$H$28,MATCH("IV-"&RIGHT($A7,2),Series!$A$5:$A$28,0)),"n.d.") -> 9 | F7: =IFERROR(ROUND(AVERAGEIFS(Series!$K$5:$K$28,Series!$B$5:$B$28,$A7),3),"n.d.") -> 37.675 | G7: =IFERROR(ROUND(AVERAGEIFS(Series!$L$5:$L$28,Series!$B$5:$B$28,$A7),3),"n.d.") -> 35.85 | H7: =IFERROR(ROUND(AVERAGEIFS(Series!$M$5:$M$28,Series!$B$5:$B$28,$A7),3),"n.d.") -> 51.75 | I7: =IFERROR(ROUND(AVERAGEIFS(Series!$N$5:$N$28,Series!$B$5:$B$28,$A7),3),"n.d.") -> 15.9 | J7: =IFERROR(ROUND(AVERAGEIFS(Series!$O$5:$O$28,Series!$B$5:$B$28,$A7),3),"n.d.") -> n.d. | K7: =IFERROR(ROUND(AVERAGEIFS(Series!$P$5:$P$28,Series!$B$5:$B$28,$A7),3),"n.d.") -> n.d. | L7: =IFERROR(ROUND(AVERAGEIFS(Series!$Q$5:$Q$28,Series!$B$5:$B$28,$A7),3),"n.d.") -> n.d. | M7: =IFERROR(ROUND(AVERAGEIFS(Series!$R$5:$R$28,Series!$B$5:$B$28,$A7),3),"n.d.") -> 52.975 | N7: =IFERROR(ROUND(AVERAGEIFS(Series!$T$5:$T$28,Series!$B$5:$B$28,$A7),3),"n.d.") -> 18.75 | O7: =IFERROR(ROUND(AVERAGEIFS(Series!$V$5:$V$28,Series!$B$5:$B$28,$A7),3),"n.d.") -> n.d. | P7: =IFERROR(ROUND(AVERAGEIFS(Series!$AH$5:$AH$28,Series!$B$5:$B$28,$A7),3),"n.d.") -> n.d. | Q7: =IFERROR(ROUND(AVERAGEIFS(Series!$AE$5:$AE$28,Series!$B$5:$B$28,$A7),5),"n.d.") -> n.d. | R7: =IFERROR(AVERAGEIFS(Series!$F$5:$F$28,Series!$B$5:$B$28,$A7),"n.d.") -> 4.625 | S7: =IFERROR(AVERAGEIFS(Series!$G$5:$G$28,Series!$B$5:$B$28,$A7),"pend.") -> pend. | T7: 2021
A8: 2022 | B8: Diseño vigente | C8: =COUNTIFS(Series!$B$5:$B$28,$A8,Series!$H$5:$H$28,"<>") -> 4 | D8: =IFERROR(ROUND(AVERAGEIFS(Series!$H$5:$H$28,Series!$B$5:$B$28,$A8),3),"n.d.") -> 15.35 | E8: =IFERROR(INDEX(Series!$H$5:$H$28,MATCH("IV-"&RIGHT($A8,2),Series!$A$5:$A$28,0)),"n.d.") -> 13.8 | F8: =IFERROR(ROUND(AVERAGEIFS(Series!$K$5:$K$28,Series!$B$5:$B$28,$A8),3),"n.d.") -> 39.275 | G8: =IFERROR(ROUND(AVERAGEIFS(Series!$L$5:$L$28,Series!$B$5:$B$28,$A8),3),"n.d.") -> 38.425 | H8: =IFERROR(ROUND(AVERAGEIFS(Series!$M$5:$M$28,Series!$B$5:$B$28,$A8),3),"n.d.") -> 45.9 | I8: =IFERROR(ROUND(AVERAGEIFS(Series!$N$5:$N$28,Series!$B$5:$B$28,$A8),3),"n.d.") -> 7.475 | J8: =IFERROR(ROUND(AVERAGEIFS(Series!$O$5:$O$28,Series!$B$5:$B$28,$A8),3),"n.d.") -> 13 | K8: =IFERROR(ROUND(AVERAGEIFS(Series!$P$5:$P$28,Series!$B$5:$B$28,$A8),3),"n.d.") -> 20.5 | L8: =IFERROR(ROUND(AVERAGEIFS(Series!$Q$5:$Q$28,Series!$B$5:$B$28,$A8),3),"n.d.") -> 7.5 | M8: =IFERROR(ROUND(AVERAGEIFS(Series!$R$5:$R$28,Series!$B$5:$B$28,$A8),3),"n.d.") -> 54.325 | N8: =IFERROR(ROUND(AVERAGEIFS(Series!$T$5:$T$28,Series!$B$5:$B$28,$A8),3),"n.d.") -> 19.2 | O8: =IFERROR(ROUND(AVERAGEIFS(Series!$V$5:$V$28,Series!$B$5:$B$28,$A8),3),"n.d.") -> 28.55 | P8: =IFERROR(ROUND(AVERAGEIFS(Series!$AH$5:$AH$28,Series!$B$5:$B$28,$A8),3),"n.d.") -> 23.75 | Q8: =IFERROR(ROUND(AVERAGEIFS(Series!$AE$5:$AE$28,Series!$B$5:$B$28,$A8),5),"n.d.") -> 0.14026 | R8: =IFERROR(AVERAGEIFS(Series!$F$5:$F$28,Series!$B$5:$B$28,$A8),"n.d.") -> 8.5 | S8: =IFERROR(AVERAGEIFS(Series!$G$5:$G$28,Series!$B$5:$B$28,$A8),"pend.") -> pend. | T8: 2022
A9: 2023 | B9: Diseño vigente | C9: =COUNTIFS(Series!$B$5:$B$28,$A9,Series!$H$5:$H$28,"<>") -> 4 | D9: =IFERROR(ROUND(AVERAGEIFS(Series!$H$5:$H$28,Series!$B$5:$B$28,$A9),3),"n.d.") -> 15.375 | E9: =IFERROR(INDEX(Series!$H$5:$H$28,MATCH("IV-"&RIGHT($A9,2),Series!$A$5:$A$28,0)),"n.d.") -> 15.6 | F9: =IFERROR(ROUND(AVERAGEIFS(Series!$K$5:$K$28,Series!$B$5:$B$28,$A9),3),"n.d.") -> 37.775 | G9: =IFERROR(ROUND(AVERAGEIFS(Series!$L$5:$L$28,Series!$B$5:$B$28,$A9),3),"n.d.") -> 36.975 | H9: =IFERROR(ROUND(AVERAGEIFS(Series!$M$5:$M$28,Series!$B$5:$B$28,$A9),3),"n.d.") -> 43.725 | I9: =IFERROR(ROUND(AVERAGEIFS(Series!$N$5:$N$28,Series!$B$5:$B$28,$A9),3),"n.d.") -> 6.75 | J9: =IFERROR(ROUND(AVERAGEIFS(Series!$O$5:$O$28,Series!$B$5:$B$28,$A9),3),"n.d.") -> 14.65 | K9: =IFERROR(ROUND(AVERAGEIFS(Series!$P$5:$P$28,Series!$B$5:$B$28,$A9),3),"n.d.") -> 20.1 | L9: =IFERROR(ROUND(AVERAGEIFS(Series!$Q$5:$Q$28,Series!$B$5:$B$28,$A9),3),"n.d.") -> 5.45 | M9: =IFERROR(ROUND(AVERAGEIFS(Series!$R$5:$R$28,Series!$B$5:$B$28,$A9),3),"n.d.") -> 57.6 | N9: =IFERROR(ROUND(AVERAGEIFS(Series!$T$5:$T$28,Series!$B$5:$B$28,$A9),3),"n.d.") -> 16.75 | O9: =IFERROR(ROUND(AVERAGEIFS(Series!$V$5:$V$28,Series!$B$5:$B$28,$A9),3),"n.d.") -> 29.25 | P9: =IFERROR(ROUND(AVERAGEIFS(Series!$AH$5:$AH$28,Series!$B$5:$B$28,$A9),3),"n.d.") -> 31.025 | Q9: =IFERROR(ROUND(AVERAGEIFS(Series!$AE$5:$AE$28,Series!$B$5:$B$28,$A9),5),"n.d.") -> 0.07243 | R9: =IFERROR(AVERAGEIFS(Series!$F$5:$F$28,Series!$B$5:$B$28,$A9),"n.d.") -> 11.25 | S9: =IFERROR(AVERAGEIFS(Series!$G$5:$G$28,Series!$B$5:$B$28,$A9),"pend.") -> pend. | T9: 2023
A10: 2024 | B10: Diseño vigente | C10: =COUNTIFS(Series!$B$5:$B$28,$A10,Series!$H$5:$H$28,"<>") -> 4 | D10: =IFERROR(ROUND(AVERAGEIFS(Series!$H$5:$H$28,Series!$B$5:$B$28,$A10),3),"n.d.") -> 14.125 | E10: =IFERROR(INDEX(Series!$H$5:$H$28,MATCH("IV-"&RIGHT($A10,2),Series!$A$5:$A$28,0)),"n.d.") -> 12.1 | F10: =IFERROR(ROUND(AVERAGEIFS(Series!$K$5:$K$28,Series!$B$5:$B$28,$A10),3),"n.d.") -> 38.95 | G10: =IFERROR(ROUND(AVERAGEIFS(Series!$L$5:$L$28,Series!$B$5:$B$28,$A10),3),"n.d.") -> 37.9 | H10: =IFERROR(ROUND(AVERAGEIFS(Series!$M$5:$M$28,Series!$B$5:$B$28,$A10),3),"n.d.") -> 47.05 | I10: =IFERROR(ROUND(AVERAGEIFS(Series!$N$5:$N$28,Series!$B$5:$B$28,$A10),3),"n.d.") -> 9.15 | J10: =IFERROR(ROUND(AVERAGEIFS(Series!$O$5:$O$28,Series!$B$5:$B$28,$A10),3),"n.d.") -> 12.8 | K10: =IFERROR(ROUND(AVERAGEIFS(Series!$P$5:$P$28,Series!$B$5:$B$28,$A10),3),"n.d.") -> 21.267 | L10: =IFERROR(ROUND(AVERAGEIFS(Series!$Q$5:$Q$28,Series!$B$5:$B$28,$A10),3),"n.d.") -> 8.467 | M10: =IFERROR(ROUND(AVERAGEIFS(Series!$R$5:$R$28,Series!$B$5:$B$28,$A10),3),"n.d.") -> 56.15 | N10: =IFERROR(ROUND(AVERAGEIFS(Series!$T$5:$T$28,Series!$B$5:$B$28,$A10),3),"n.d.") -> 18.65 | O10: =IFERROR(ROUND(AVERAGEIFS(Series!$V$5:$V$28,Series!$B$5:$B$28,$A10),3),"n.d.") -> 28.55 | P10: =IFERROR(ROUND(AVERAGEIFS(Series!$AH$5:$AH$28,Series!$B$5:$B$28,$A10),3),"n.d.") -> 32.4 | Q10: =IFERROR(ROUND(AVERAGEIFS(Series!$AE$5:$AE$28,Series!$B$5:$B$28,$A10),5),"n.d.") -> 0.0697 | R10: =IFERROR(AVERAGEIFS(Series!$F$5:$F$28,Series!$B$5:$B$28,$A10),"n.d.") -> 10.625 | S10: =IFERROR(AVERAGEIFS(Series!$G$5:$G$28,Series!$B$5:$B$28,$A10),"pend.") -> pend. | T10: 2024
A11: 2025 | B11: Diseño vigente | C11: =COUNTIFS(Series!$B$5:$B$28,$A11,Series!$H$5:$H$28,"<>") -> 4 | D11: =IFERROR(ROUND(AVERAGEIFS(Series!$H$5:$H$28,Series!$B$5:$B$28,$A11),3),"n.d.") -> 13.75 | E11: =IFERROR(INDEX(Series!$H$5:$H$28,MATCH("IV-"&RIGHT($A11,2),Series!$A$5:$A$28,0)),"n.d.") -> 15.3 | F11: =IFERROR(ROUND(AVERAGEIFS(Series!$K$5:$K$28,Series!$B$5:$B$28,$A11),3),"n.d.") -> 37.3 | G11: =IFERROR(ROUND(AVERAGEIFS(Series!$L$5:$L$28,Series!$B$5:$B$28,$A11),3),"n.d.") -> 36.125 | H11: =IFERROR(ROUND(AVERAGEIFS(Series!$M$5:$M$28,Series!$B$5:$B$28,$A11),3),"n.d.") -> 46.35 | I11: =IFERROR(ROUND(AVERAGEIFS(Series!$N$5:$N$28,Series!$B$5:$B$28,$A11),3),"n.d.") -> 10.225 | J11: =IFERROR(ROUND(AVERAGEIFS(Series!$O$5:$O$28,Series!$B$5:$B$28,$A11),3),"n.d.") -> 14.3 | K11: =IFERROR(ROUND(AVERAGEIFS(Series!$P$5:$P$28,Series!$B$5:$B$28,$A11),3),"n.d.") -> 21.8 | L11: =IFERROR(ROUND(AVERAGEIFS(Series!$Q$5:$Q$28,Series!$B$5:$B$28,$A11),3),"n.d.") -> 7.5 | M11: =IFERROR(ROUND(AVERAGEIFS(Series!$R$5:$R$28,Series!$B$5:$B$28,$A11),3),"n.d.") -> 54.8 | N11: =IFERROR(ROUND(AVERAGEIFS(Series!$T$5:$T$28,Series!$B$5:$B$28,$A11),3),"n.d.") -> 18.475 | O11: =IFERROR(ROUND(AVERAGEIFS(Series!$V$5:$V$28,Series!$B$5:$B$28,$A11),3),"n.d.") -> 27.25 | P11: =IFERROR(ROUND(AVERAGEIFS(Series!$AH$5:$AH$28,Series!$B$5:$B$28,$A11),3),"n.d.") -> 45.65 | Q11: =IFERROR(ROUND(AVERAGEIFS(Series!$AE$5:$AE$28,Series!$B$5:$B$28,$A11),5),"n.d.") -> 0.06352 | R11: =IFERROR(AVERAGEIFS(Series!$F$5:$F$28,Series!$B$5:$B$28,$A11),"n.d.") -> 7.875 | S11: =IFERROR(AVERAGEIFS(Series!$G$5:$G$28,Series!$B$5:$B$28,$A11),"pend.") -> pend. | T11: 2025
A12: 2026 | B12: Diseño vigente (I-II; III pendiente) | C12: =COUNTIFS(Series!$B$5:$B$28,$A12,Series!$H$5:$H$28,"<>") -> 2 | D12: =IFERROR(ROUND(AVERAGEIFS(Series!$H$5:$H$28,Series!$B$5:$B$28,$A12),3),"n.d.") -> 12.15 | E12: =IFERROR(INDEX(Series!$H$5:$H$28,MATCH("IV-"&RIGHT($A12,2),Series!$A$5:$A$28,0)),"n.d.") -> n.d. | F12: =IFERROR(ROUND(AVERAGEIFS(Series!$K$5:$K$28,Series!$B$5:$B$28,$A12),3),"n.d.") -> 37.15 | G12: =IFERROR(ROUND(AVERAGEIFS(Series!$L$5:$L$28,Series!$B$5:$B$28,$A12),3),"n.d.") -> 35.75 | H12: =IFERROR(ROUND(AVERAGEIFS(Series!$M$5:$M$28,Series!$B$5:$B$28,$A12),3),"n.d.") -> 48.1 | I12: =IFERROR(ROUND(AVERAGEIFS(Series!$N$5:$N$28,Series!$B$5:$B$28,$A12),3),"n.d.") -> 12.35 | J12: =IFERROR(ROUND(AVERAGEIFS(Series!$O$5:$O$28,Series!$B$5:$B$28,$A12),3),"n.d.") -> 11 | K12: =IFERROR(ROUND(AVERAGEIFS(Series!$P$5:$P$28,Series!$B$5:$B$28,$A12),3),"n.d.") -> 21 | L12: =IFERROR(ROUND(AVERAGEIFS(Series!$Q$5:$Q$28,Series!$B$5:$B$28,$A12),3),"n.d.") -> 10 | M12: =IFERROR(ROUND(AVERAGEIFS(Series!$R$5:$R$28,Series!$B$5:$B$28,$A12),3),"n.d.") -> 53.5 | N12: =IFERROR(ROUND(AVERAGEIFS(Series!$T$5:$T$28,Series!$B$5:$B$28,$A12),3),"n.d.") -> 19.45 | O12: =IFERROR(ROUND(AVERAGEIFS(Series!$V$5:$V$28,Series!$B$5:$B$28,$A12),3),"n.d.") -> 24.75 | P12: =IFERROR(ROUND(AVERAGEIFS(Series!$AH$5:$AH$28,Series!$B$5:$B$28,$A12),3),"n.d.") -> 42.15 | Q12: =IFERROR(ROUND(AVERAGEIFS(Series!$AE$5:$AE$28,Series!$B$5:$B$28,$A12),5),"n.d.") -> 0.23405 | R12: =IFERROR(AVERAGEIFS(Series!$F$5:$F$28,Series!$B$5:$B$28,$A12),"n.d.") -> 6.5833333 | S12: =IFERROR(AVERAGEIFS(Series!$G$5:$G$28,Series!$B$5:$B$28,$A12),"pend.") -> pend. | T12: 2026 (I-II)
A14: n.d. = sin dato publicado en los comunicados revisados. Nuevo crédito por tamaño: promedio de los trimestres con dato (ver hoja Por tamaño).
A15: ¿Acumulado? No: el IV trimestre (columna E) mide solo octubre-diciembre. Por eso el dato anual es el promedio de los trimestres (columna D), no el IV trimestre.
A16: 2020: la muestra anterior y el diseño vigente no son comparables en nivel (la anterior da ~5.8 pp más de crédito nuevo). Para la tendencia 2021-2026 usar solo el diseño vigente.
A17: Tasa objetivo y TIIE de 2026 incluyen III-26 (la tasa ya se conoce: 6.50%); las variables de la encuesta solo I y II.
A36: Fuente: Banxico, comunicados de la Encuesta de Evaluación Coyuntural del Mercado Crediticio (muestra anterior para 2020 I-IV; diseño vigente IV-2020 a II-2026). Promedio simple de trimestres; barra gris = dato del IV trimestre. Datos: columnas D y E de esta hoja.

Sheet Por tamaño
A1: Gran empresa vs pequeñas y medianas, 2020-2026
A2: Banxico divide por número de empleados: 'hasta 100' (11 a 100; pequeñas y parte de las medianas) y 'más de 100' (resto de medianas y grandes). % de empresas de cada tamaño.
A4: Cuadro A. Gran empresa (más de 100 empleados) | I4: Cuadro B. Pequeñas y medianas (11 a 100 empleados)
A5: Trimestre | B5: Año | C5: Con crédito al inicio (%) | D5: Usaron nuevo crédito (%) | E5: ID tasas de interés (índice) | F5: Banca comercial como fuente (%) | G5: Tasa de rechazo (%) | I5: Trimestre | J5: Año | K5: Con crédito al inicio (%) | L5: Usaron nuevo crédito (%) | M5: ID tasas de interés (índice) | N5: Banca comercial como fuente (%) | O5: Tasa de rechazo (%)
A6: I-20 | B6: 2020 | C6: n.d. | D6: n.d. | E6: n.d. | F6: n.d. | G6: n.d. | I6: I-20 | J6: 2020 | K6: n.d. | L6: n.d. | M6: n.d. | N6: n.d. | O6: n.d.
A7: II-20 | B7: 2020 | C7: n.d. | D7: n.d. | E7: n.d. | F7: n.d. | G7: n.d. | I7: II-20 | J7: 2020 | K7: n.d. | L7: n.d. | M7: n.d. | N7: n.d. | O7: n.d.
A8: III-20 | B8: 2020 | C8: n.d. | D8: n.d. | E8: n.d. | F8: n.d. | G8: n.d. | I8: III-20 | J8: 2020 | K8: n.d. | L8: n.d. | M8: n.d. | N8: n.d. | O8: n.d.
A9: IV-20 | B9: 2020 | C9: =IF(Series!M5="","n.d.",Series!M5) -> 46.9 | D9: =IF(Series!P5="","n.d.",Series!P5) -> n.d. | E9: =IF(Series!AJ5="","n.d.",Series!AJ5) -> n.d. | F9: =IF(Series!X5="","n.d.",Series!X5) -> n.d. | G9: =IF(Series!AG5="","n.d.",Series!AG5) -> n.d. | I9: IV-20 | J9: 2020 | K9: =IF(Series!L5="","n.d.",Series!L5) -> 38.7 | L9: =IF(Series!O5="","n.d.",Series!O5) -> n.d. | M9: =IF(Series!AI5="","n.d.",Series!AI5) -> n.d. | N9: =IF(Series!W5="","n.d.",Series!W5) -> n.d. | O9: =IF(Series!AF5="","n.d.",Series!AF5) -> n.d.
A10: I-21 | B10: 2021 | C10: =IF(Series!M6="","n.d.",Series!M6) -> 51.9 | D10: =IF(Series!P6="","n.d.",Series!P6) -> n.d. | E10: =IF(Series!AJ6="","n.d.",Series!AJ6) -> n.d. | F10: =IF(Series!X6="","n.d.",Series!X6) -> n.d. | G10: =IF(Series!AG6="","n.d.",Series!AG6) -> n.d. | I10: I-21 | J10: 2021 | K10: =IF(Series!L6="","n.d.",Series!L6) -> 37.5 | L10: =IF(Series!O6="","n.d.",Series!O6) -> n.d. | M10: =IF(Series!AI6="","n.d.",Series!AI6) -> n.d. | N10: =IF(Series!W6="","n.d.",Series!W6) -> n.d. | O10: =IF(Series!AF6="","n.d.",Series!AF6) -> n.d.
A11: II-21 | B11: 2021 | C11: =IF(Series!M7="","n.d.",Series!M7) -> 48.6 | D11: =IF(Series!P7="","n.d.",Series!P7) -> n.d. | E11: =IF(Series!AJ7="","n.d.",Series!AJ7) -> n.d. | F11: =IF(Series!X7="","n.d.",Series!X7) -> n.d. | G11: =IF(Series!AG7="","n.d.",Series!AG7) -> n.d. | I11: II-21 | J11: 2021 | K11: =IF(Series!L7="","n.d.",Series!L7) -> 35 | L11: =IF(Series!O7="","n.d.",Series!O7) -> n.d. | M11: =IF(Series!AI7="","n.d.",Series!AI7) -> n.d. | N11: =IF(Series!W7="","n.d.",Series!W7) -> n.d. | O11: =IF(Series!AF7="","n.d.",Series!AF7) -> n.d.
A12: III-21 | B12: 2021 | C12: =IF(Series!M8="","n.d.",Series!M8) -> 52.1 | D12: =IF(Series!P8="","n.d.",Series!P8) -> n.d. | E12: =IF(Series!AJ8="","n.d.",Series!AJ8) -> n.d. | F12: =IF(Series!X8="","n.d.",Series!X8) -> n.d. | G12: =IF(Series!AG8="","n.d.",Series!AG8) -> n.d. | I12: III-21 | J12: 2021 | K12: =IF(Series!L8="","n.d.",Series!L8) -> 35.6 | L12: =IF(Series!O8="","n.d.",Series!O8) -> n.d. | M12: =IF(Series!AI8="","n.d.",Series!AI8) -> n.d. | N12: =IF(Series!W8="","n.d.",Series!W8) -> n.d. | O12: =IF(Series!AF8="","n.d.",Series!AF8) -> n.d.
A13: IV-21 | B13: 2021 | C13: =IF(Series!M9="","n.d.",Series!M9) -> 54.4 | D13: =IF(Series!P9="","n.d.",Series!P9) -> n.d. | E13: =IF(Series!AJ9="","n.d.",Series!AJ9) -> n.d. | F13: =IF(Series!X9="","n.d.",Series!X9) -> n.d. | G13: =IF(Series!AG9="","n.d.",Series!AG9) -> n.d. | I13: IV-21 | J13: 2021 | K13: =IF(Series!L9="","n.d.",Series!L9) -> 35.3 | L13: =IF(Series!O9="","n.d.",Series!O9) -> n.d. | M13: =IF(Series!AI9="","n.d.",Series!AI9) -> n.d. | N13: =IF(Series!W9="","n.d.",Series!W9) -> n.d. | O13: =IF(Series!AF9="","n.d.",Series!AF9) -> n.d.
A14: I-22 | B14: 2022 | C14: =IF(Series!M10="","n.d.",Series!M10) -> 47.8 | D14: =IF(Series!P10="","n.d.",Series!P10) -> n.d. | E14: =IF(Series!AJ10="","n.d.",Series!AJ10) -> n.d. | F14: =IF(Series!X10="","n.d.",Series!X10) -> n.d. | G14: =IF(Series!AG10="","n.d.",Series!AG10) -> n.d. | I14: I-22 | J14: 2022 | K14: =IF(Series!L10="","n.d.",Series!L10) -> 41.1 | L14: =IF(Series!O10="","n.d.",Series!O10) -> n.d. | M14: =IF(Series!AI10="","n.d.",Series!AI10) -> n.d. | N14: =IF(Series!W10="","n.d.",Series!W10) -> n.d. | O14: =IF(Series!AF10="","n.d.",Series!AF10) -> n.d.
A15: II-22 | B15: 2022 | C15: =IF(Series!M11="","n.d.",Series!M11) -> 51.8 | D15: =IF(Series!P11="","n.d.",Series!P11) -> n.d. | E15: =IF(Series!AJ11="","n.d.",Series!AJ11) -> n.d. | F15: =IF(Series!X11="","n.d.",Series!X11) -> n.d. | G15: =IF(Series!AG11="","n.d.",Series!AG11) -> n.d. | I15: II-22 | J15: 2022 | K15: =IF(Series!L11="","n.d.",Series!L11) -> 38.7 | L15: =IF(Series!O11="","n.d.",Series!O11) -> n.d. | M15: =IF(Series!AI11="","n.d.",Series!AI11) -> n.d. | N15: =IF(Series!W11="","n.d.",Series!W11) -> n.d. | O15: =IF(Series!AF11="","n.d.",Series!AF11) -> n.d.
A16: III-22 | B16: 2022 | C16: =IF(Series!M12="","n.d.",Series!M12) -> 45.1 | D16: =IF(Series!P12="","n.d.",Series!P12) -> n.d. | E16: =IF(Series!AJ12="","n.d.",Series!AJ12) -> n.d. | F16: =IF(Series!X12="","n.d.",Series!X12) -> n.d. | G16: =IF(Series!AG12="","n.d.",Series!AG12) -> n.d. | I16: III-22 | J16: 2022 | K16: =IF(Series!L12="","n.d.",Series!L12) -> 37 | L16: =IF(Series!O12="","n.d.",Series!O12) -> n.d. | M16: =IF(Series!AI12="","n.d.",Series!AI12) -> n.d. | N16: =IF(Series!W12="","n.d.",Series!W12) -> n.d. | O16: =IF(Series!AF12="","n.d.",Series!AF12) -> n.d.
A17: IV-22 | B17: 2022 | C17: =IF(Series!M13="","n.d.",Series!M13) -> 38.9 | D17: =IF(Series!P13="","n.d.",Series!P13) -> 20.5 | E17: =IF(Series!AJ13="","n.d.",Series!AJ13) -> n.d. | F17: =IF(Series!X13="","n.d.",Series!X13) -> n.d. | G17: =IF(Series!AG13="","n.d.",Series!AG13) -> n.d. | I17: IV-22 | J17: 2022 | K17: =IF(Series!L13="","n.d.",Series!L13) -> 36.9 | L17: =IF(Series!O13="","n.d.",Series!O13) -> 13 | M17: =IF(Series!AI13="","n.d.",Series!AI13) -> n.d. | N17: =IF(Series!W13="","n.d.",Series!W13) -> n.d. | O17: =IF(Series!AF13="","n.d.",Series!AF13) -> n.d.
A18: I-23 | B18: 2023 | C18: =IF(Series!M14="","n.d.",Series!M14) -> 44.8 | D18: =IF(Series!P14="","n.d.",Series!P14) -> n.d. | E18: =IF(Series!AJ14="","n.d.",Series!AJ14) -> n.d. | F18: =IF(Series!X14="","n.d.",Series!X14) -> n.d. | G18: =IF(Series!AG14="","n.d.",Series!AG14) -> n.d. | I18: I-23 | J18: 2023 | K18: =IF(Series!L14="","n.d.",Series!L14) -> 35.7 | L18: =IF(Series!O14="","n.d.",Series!O14) -> n.d. | M18: =IF(Series!AI14="","n.d.",Series!AI14) -> n.d. | N18: =IF(Series!W14="","n.d.",Series!W14) -> n.d. | O18: =IF(Series!AF14="","n.d.",Series!AF14) -> n.d.
A19: II-23 | B19: 2023 | C19: =IF(Series!M15="","n.d.",Series!M15) -> 43.4 | D19: =IF(Series!P15="","n.d.",Series!P15) -> 21.6 | E19: =IF(Series!AJ15="","n.d.",Series!AJ15) -> n.d. | F19: =IF(Series!X15="","n.d.",Series!X15) -> n.d. | G19: =IF(Series!AG15="","n.d.",Series!AG15) -> n.d. | I19: II-23 | J19: 2023 | K19: =IF(Series!L15="","n.d.",Series!L15) -> 36.6 | L19: =IF(Series!O15="","n.d.",Series!O15) -> 14 | M19: =IF(Series!AI15="","n.d.",Series!AI15) -> n.d. | N19: =IF(Series!W15="","n.d.",Series!W15) -> n.d. | O19: =IF(Series!AF15="","n.d.",Series!AF15) -> n.d.
A20: III-23 | B20: 2023 | C20: =IF(Series!M16="","n.d.",Series!M16) -> 42.4 | D20: =IF(Series!P16="","n.d.",Series!P16) -> n.d. | E20: =IF(Series!AJ16="","n.d.",Series!AJ16) -> n.d. | F20: =IF(Series!X16="","n.d.",Series!X16) -> n.d. | G20: =IF(Series!AG16="","n.d.",Series!AG16) -> n.d. | I20: III-23 | J20: 2023 | K20: =IF(Series!L16="","n.d.",Series!L16) -> 35.5 | L20: =IF(Series!O16="","n.d.",Series!O16) -> n.d. | M20: =IF(Series!AI16="","n.d.",Series!AI16) -> n.d. | N20: =IF(Series!W16="","n.d.",Series!W16) -> n.d. | O20: =IF(Series!AF16="","n.d.",Series!AF16) -> n.d.
... A32: III-26 | B32: 2026 | C32: =IF(Series!M28="","n.d.",Series!M28) -> n.d. | D32: =IF(Series!P28="","n.d.",Series!P28) -> n.d. | E32: =IF(Series!AJ28="","n.d.",Series!AJ28) -> n.d. | F32: =IF(Series!X28="","n.d.",Series!X28) -> n.d. | G32: =IF(Series!AG28="","n.d.",Series!AG28) -> n.d. | I32: III-26 | J32: 2026 | K32: =IF(Series!L28="","n.d.",Series!L28) -> n.d. | L32: =IF(Series!O28="","n.d.",Series!O28) -> n.d. | M32: =IF(Series!AI28="","n.d.",Series!AI28) -> n.d. | N32: =IF(Series!W28="","n.d.",Series!W28) -> n.d. | O32: =IF(Series!AF28="","n.d.",Series!AF28) -> n.d.
A33: n.d. = no publicado en los comunicados revisados o pendiente de descargar del SIE (CF910). I-III 2020: la muestra anterior no se capturó por tamaño. III-2026: se publica el 19-nov-2026.
A35: Cuadro C. Resumen anual por tamaño y brecha (promedio de trimestres con dato)
A36: Año | B36: Con crédito — hasta 100 (%) | C36: Con crédito — más de 100 (%) | D36: Brecha con crédito (pp) | E36: Nuevo crédito — hasta 100 (%) | F36: Nuevo crédito — más de 100 (%) | G36: Brecha nuevo crédito (pp) | H36: Trimestres con dato de nuevo crédito por tamaño | I36: ID tasas — hasta 100 | J36: ID tasas — más de 100
A37: 2020 | B37: =IFERROR(ROUND(AVERAGEIFS(Series!$L$5:$L$28,Series!$B$5:$B$28,$A37),3),"n.d.") -> 38.7 | C37: =IFERROR(ROUND(AVERAGEIFS(Series!$M$5:$M$28,Series!$B$5:$B$28,$A37),3),"n.d.") -> 46.9 | D37: =IFERROR(ROUND(AVERAGEIFS(Series!$N$5:$N$28,Series!$B$5:$B$28,$A37),3),"n.d.") -> 8.2 | E37: =IFERROR(ROUND(AVERAGEIFS(Series!$O$5:$O$28,Series!$B$5:$B$28,$A37),3),"n.d.") -> n.d. | F37: =IFERROR(ROUND(AVERAGEIFS(Series!$P$5:$P$28,Series!$B$5:$B$28,$A37),3),"n.d.") -> n.d. | G37: =IFERROR(ROUND(AVERAGEIFS(Series!$Q$5:$Q$28,Series!$B$5:$B$28,$A37),3),"n.d.") -> n.d. | H37: =COUNTIFS(Series!$B$5:$B$28,$A37,Series!$O$5:$O$28,"<>") -> 0 | I37: =IFERROR(ROUND(AVERAGEIFS(Series!$AI$5:$AI$28,Series!$B$5:$B$28,$A37),3),"n.d.") -> n.d. | J37: =IFERROR(ROUND(AVERAGEIFS(Series!$AJ$5:$AJ$28,Series!$B$5:$B$28,$A37),3),"n.d.") -> n.d.
A38: 2021 | B38: =IFERROR(ROUND(AVERAGEIFS(Series!$L$5:$L$28,Series!$B$5:$B$28,$A38),3),"n.d.") -> 35.85 | C38: =IFERROR(ROUND(AVERAGEIFS(Series!$M$5:$M$28,Series!$B$5:$B$28,$A38),3),"n.d.") -> 51.75 | D38: =IFERROR(ROUND(AVERAGEIFS(Series!$N$5:$N$28,Series!$B$5:$B$28,$A38),3),"n.d.") -> 15.9 | E38: =IFERROR(ROUND(AVERAGEIFS(Series!$O$5:$O$28,Series!$B$5:$B$28,$A38),3),"n.d.") -> n.d. | F38: =IFERROR(ROUND(AVERAGEIFS(Series!$P$5:$P$28,Series!$B$5:$B$28,$A38),3),"n.d.") -> n.d. | G38: =IFERROR(ROUND(AVERAGEIFS(Series!$Q$5:$Q$28,Series!$B$5:$B$28,$A38),3),"n.d.") -> n.d. | H38: =COUNTIFS(Series!$B$5:$B$28,$A38,Series!$O$5:$O$28,"<>") -> 0 | I38: =IFERROR(ROUND(AVERAGEIFS(Series!$AI$5:$AI$28,Series!$B$5:$B$28,$A38),3),"n.d.") -> n.d. | J38: =IFERROR(ROUND(AVERAGEIFS(Series!$AJ$5:$AJ$28,Series!$B$5:$B$28,$A38),3),"n.d.") -> n.d.
A39: 2022 | B39: =IFERROR(ROUND(AVERAGEIFS(Series!$L$5:$L$28,Series!$B$5:$B$28,$A39),3),"n.d.") -> 38.425 | C39: =IFERROR(ROUND(AVERAGEIFS(Series!$M$5:$M$28,Series!$B$5:$B$28,$A39),3),"n.d.") -> 45.9 | D39: =IFERROR(ROUND(AVERAGEIFS(Series!$N$5:$N$28,Series!$B$5:$B$28,$A39),3),"n.d.") -> 7.475 | E39: =IFERROR(ROUND(AVERAGEIFS(Series!$O$5:$O$28,Series!$B$5:$B$28,$A39),3),"n.d.") -> 13 | F39: =IFERROR(ROUND(AVERAGEIFS(Series!$P$5:$P$28,Series!$B$5:$B$28,$A39),3),"n.d.") -> 20.5 | G39: =IFERROR(ROUND(AVERAGEIFS(Series!$Q$5:$Q$28,Series!$B$5:$B$28,$A39),3),"n.d.") -> 7.5 | H39: =COUNTIFS(Series!$B$5:$B$28,$A39,Series!$O$5:$O$28,"<>") -> 1 | I39: =IFERROR(ROUND(AVERAGEIFS(Series!$AI$5:$AI$28,Series!$B$5:$B$28,$A39),3),"n.d.") -> n.d. | J39: =IFERROR(ROUND(AVERAGEIFS(Series!$AJ$5:$AJ$28,Series!$B$5:$B$28,$A39),3),"n.d.") -> n.d.
A40: 2023 | B40: =IFERROR(ROUND(AVERAGEIFS(Series!$L$5:$L$28,Series!$B$5:$B$28,$A40),3),"n.d.") -> 36.975 | C40: =IFERROR(ROUND(AVERAGEIFS(Series!$M$5:$M$28,Series!$B$5:$B$28,$A40),3),"n.d.") -> 43.725 | D40: =IFERROR(ROUND(AVERAGEIFS(Series!$N$5:$N$28,Series!$B$5:$B$28,$A40),3),"n.d.") -> 6.75 | E40: =IFERROR(ROUND(AVERAGEIFS(Series!$O$5:$O$28,Series!$B$5:$B$28,$A40),3),"n.d.") -> 14.65 | F40: =IFERROR(ROUND(AVERAGEIFS(Series!$P$5:$P$28,Series!$B$5:$B$28,$A40),3),"n.d.") -> 20.1 | G40: =IFERROR(ROUND(AVERAGEIFS(Series!$Q$5:$Q$28,Series!$B$5:$B$28,$A40),3),"n.d.") -> 5.45 | H40: =COUNTIFS(Series!$B$5:$B$28,$A40,Series!$O$5:$O$28,"<>") -> 2 | I40: =IFERROR(ROUND(AVERAGEIFS(Series!$AI$5:$AI$28,Series!$B$5:$B$28,$A40),3),"n.d.") -> n.d. | J40: =IFERROR(ROUND(AVERAGEIFS(Series!$AJ$5:$AJ$28,Series!$B$5:$B$28,$A40),3),"n.d.") -> n.d.
A41: 2024 | B41: =IFERROR(ROUND(AVERAGEIFS(Series!$L$5:$L$28,Series!$B$5:$B$28,$A41),3),"n.d.") -> 37.9 | C41: =IFERROR(ROUND(AVERAGEIFS(Series!$M$5:$M$28,Series!$B$5:$B$28,$A41),3),"n.d.") -> 47.05 | D41: =IFERROR(ROUND(AVERAGEIFS(Series!$N$5:$N$28,Series!$B$5:$B$28,$A41),3),"n.d.") -> 9.15 | E41: =IFERROR(ROUND(AVERAGEIFS(Series!$O$5:$O$28,Series!$B$5:$B$28,$A41),3),"n.d.") -> 12.8 | F41: =IFERROR(ROUND(AVERAGEIFS(Series!$P$5:$P$28,Series!$B$5:$B$28,$A41),3),"n.d.") -> 21.267 | G41: =IFERROR(ROUND(AVERAGEIFS(Series!$Q$5:$Q$28,Series!$B$5:$B$28,$A41),3),"n.d.") -> 8.467 | H41: =COUNTIFS(Series!$B$5:$B$28,$A41,Series!$O$5:$O$28,"<>") -> 3 | I41: =IFERROR(ROUND(AVERAGEIFS(Series!$AI$5:$AI$28,Series!$B$5:$B$28,$A41),3),"n.d.") -> n.d. | J41: =IFERROR(ROUND(AVERAGEIFS(Series!$AJ$5:$AJ$28,Series!$B$5:$B$28,$A41),3),"n.d.") -> n.d.
A42: 2025 | B42: =IFERROR(ROUND(AVERAGEIFS(Series!$L$5:$L$28,Series!$B$5:$B$28,$A42),3),"n.d.") -> 36.125 | C42: =IFERROR(ROUND(AVERAGEIFS(Series!$M$5:$M$28,Series!$B$5:$B$28,$A42),3),"n.d.") -> 46.35 | D42: =IFERROR(ROUND(AVERAGEIFS(Series!$N$5:$N$28,Series!$B$5:$B$28,$A42),3),"n.d.") -> 10.225 | E42: =IFERROR(ROUND(AVERAGEIFS(Series!$O$5:$O$28,Series!$B$5:$B$28,$A42),3),"n.d.") -> 14.3 | F42: =IFERROR(ROUND(AVERAGEIFS(Series!$P$5:$P$28,Series!$B$5:$B$28,$A42),3),"n.d.") -> 21.8 | G42: =IFERROR(ROUND(AVERAGEIFS(Series!$Q$5:$Q$28,Series!$B$5:$B$28,$A42),3),"n.d.") -> 7.5 | H42: =COUNTIFS(Series!$B$5:$B$28,$A42,Series!$O$5:$O$28,"<>") -> 2 | I42: =IFERROR(ROUND(AVERAGEIFS(Series!$AI$5:$AI$28,Series!$B$5:$B$28,$A42),3),"n.d.") -> n.d. | J42: =IFERROR(ROUND(AVERAGEIFS(Series!$AJ$5:$AJ$28,Series!$B$5:$B$28,$A42),3),"n.d.") -> n.d.
A43: 2026 | B43: =IFERROR(ROUND(AVERAGEIFS(Series!$L$5:$L$28,Series!$B$5:$B$28,$A43),3),"n.d.") -> 35.75 | C43: =IFERROR(ROUND(AVERAGEIFS(Series!$M$5:$M$28,Series!$B$5:$B$28,$A43),3),"n.d.") -> 48.1 | D43: =IFERROR(ROUND(AVERAGEIFS(Series!$N$5:$N$28,Series!$B$5:$B$28,$A43),3),"n.d.") -> 12.35 | E43: =IFERROR(ROUND(AVERAGEIFS(Series!$O$5:$O$28,Series!$B$5:$B$28,$A43),3),"n.d.") -> 11 | F43: =IFERROR(ROUND(AVERAGEIFS(Series!$P$5:$P$28,Series!$B$5:$B$28,$A43),3),"n.d.") -> 21 | G43: =IFERROR(ROUND(AVERAGEIFS(Series!$Q$5:$Q$28,Series!$B$5:$B$28,$A43),3),"n.d.") -> 10 | H43: =COUNTIFS(Series!$B$5:$B$28,$A43,Series!$O$5:$O$28,"<>") -> 2 | I43: =IFERROR(ROUND(AVERAGEIFS(Series!$AI$5:$AI$28,Series!$B$5:$B$28,$A43),3),"n.d.") -> 35.3 | J43: =IFERROR(ROUND(AVERAGEIFS(Series!$AJ$5:$AJ$28,Series!$B$5:$B$28,$A43),3),"n.d.") -> 53.7
A44: 2020 = solo IV-20 (diseño vigente). 2026 = I y II trimestre. Brecha = más de 100 menos hasta 100. La brecha de nuevo crédito por año usa solo los trimestres con dato (columna H).
A63: Fuente: Banxico, comunicados de la encuesta, diseño vigente IV-2020 a II-2026. Líneas punteadas = tendencia lineal de cada tamaño. Datos: hoja Series, columnas L y M.
A82: Fuente: Banxico, comunicados IV-2022 a II-2026 (trimestres II y IV) y prensa que cita los comunicados I-2024 e I-2026. Datos: hoja Series, columnas O y P.
A101: Fuente: Cálculo propio con datos de Banxico (diseño vigente). Datos: Cuadro C de esta hoja (filas 37-43).

Sheet Rechazo y costo
A1: Rechazo y costo percibido del crédito, 2020-2026: total, pymes y grandes
A2: Tasa de rechazo = rechazadas / (rechazadas + empresas que usaron crédito nuevo). ID tasas: índice de difusión (<50 = más caro). Datos del trimestre, no acumulados.
A4: Cuadro A. Trimestral
A5: Trimestre | B5: Año | C5: Muestra | D5: Solicitaron y rechazado (% de empresas) | E5: Tasa de rechazo — total | F5: Tasa de rechazo — hasta 100 | G5: Tasa de rechazo — más de 100 | H5: ID tasas — total* | I5: ID tasas — hasta 100 | J5: ID tasas — más de 100 | K5: ID comisiones — total
A6: I-20 | B6: 2020 | C6: Anterior | D6: n.d. | E6: n.d. | F6: n.d. | G6: n.d. | H6: ='Muestra anterior'!H5 -> 61.1 | I6: n.d. | J6: n.d. | K6: n.d.
A7: II-20 | B7: 2020 | C7: Anterior | D7: n.d. | E7: n.d. | F7: n.d. | G7: n.d. | H7: ='Muestra anterior'!H6 -> 38.5 | I7: n.d. | J7: n.d. | K7: n.d.
A8: III-20 | B8: 2020 | C8: Anterior | D8: n.d. | E8: n.d. | F8: n.d. | G8: n.d. | H8: ='Muestra anterior'!H7 -> 50.8 | I8: n.d. | J8: n.d. | K8: n.d.
A9: IV-20 | B9: 2020 | C9: Anterior (ID tasas) | D9: =IF(Series!AA5="","n.d.",Series!AA5) -> n.d. | E9: =IF(Series!AE5="","n.d.",Series!AE5) -> n.d. | F9: =IF(Series!AF5="","n.d.",Series!AF5) -> n.d. | G9: =IF(Series!AG5="","n.d.",Series!AG5) -> n.d. | H9: ='Muestra anterior'!H8 -> 45.1 | I9: =IF(Series!AI5="","n.d.",Series!AI5) -> n.d. | J9: =IF(Series!AJ5="","n.d.",Series!AJ5) -> n.d. | K9: =IF(Series!AK5="","n.d.",Series!AK5) -> n.d.
A10: I-21 | B10: 2021 | C10: Anterior (ID tasas) | D10: =IF(Series!AA6="","n.d.",Series!AA6) -> n.d. | E10: =IF(Series!AE6="","n.d.",Series!AE6) -> n.d. | F10: =IF(Series!AF6="","n.d.",Series!AF6) -> n.d. | G10: =IF(Series!AG6="","n.d.",Series!AG6) -> n.d. | H10: ='Muestra anterior'!H9 -> 52.8 | I10: =IF(Series!AI6="","n.d.",Series!AI6) -> n.d. | J10: =IF(Series!AJ6="","n.d.",Series!AJ6) -> n.d. | K10: =IF(Series!AK6="","n.d.",Series!AK6) -> n.d.
A11: II-21 | B11: 2021 | C11: Anterior (ID tasas) | D11: =IF(Series!AA7="","n.d.",Series!AA7) -> n.d. | E11: =IF(Series!AE7="","n.d.",Series!AE7) -> n.d. | F11: =IF(Series!AF7="","n.d.",Series!AF7) -> n.d. | G11: =IF(Series!AG7="","n.d.",Series!AG7) -> n.d. | H11: ='Muestra anterior'!H10 -> 32.6 | I11: =IF(Series!AI7="","n.d.",Series!AI7) -> n.d. | J11: =IF(Series!AJ7="","n.d.",Series!AJ7) -> n.d. | K11: =IF(Series!AK7="","n.d.",Series!AK7) -> n.d.
A12: III-21 | B12: 2021 | C12: Anterior (ID tasas) | D12: =IF(Series!AA8="","n.d.",Series!AA8) -> n.d. | E12: =IF(Series!AE8="","n.d.",Series!AE8) -> n.d. | F12: =IF(Series!AF8="","n.d.",Series!AF8) -> n.d. | G12: =IF(Series!AG8="","n.d.",Series!AG8) -> n.d. | H12: ='Muestra anterior'!H11 -> 33.8 | I12: =IF(Series!AI8="","n.d.",Series!AI8) -> n.d. | J12: =IF(Series!AJ8="","n.d.",Series!AJ8) -> n.d. | K12: =IF(Series!AK8="","n.d.",Series!AK8) -> n.d.
A13: IV-21 | B13: 2021 | C13: Anterior (ID tasas) | D13: =IF(Series!AA9="","n.d.",Series!AA9) -> n.d. | E13: =IF(Series!AE9="","n.d.",Series!AE9) -> n.d. | F13: =IF(Series!AF9="","n.d.",Series!AF9) -> n.d. | G13: =IF(Series!AG9="","n.d.",Series!AG9) -> n.d. | H13: ='Muestra anterior'!H12 -> 27.7 | I13: =IF(Series!AI9="","n.d.",Series!AI9) -> n.d. | J13: =IF(Series!AJ9="","n.d.",Series!AJ9) -> n.d. | K13: =IF(Series!AK9="","n.d.",Series!AK9) -> n.d.
A14: I-22 | B14: 2022 | C14: Anterior (ID tasas) | D14: =IF(Series!AA10="","n.d.",Series!AA10) -> n.d. | E14: =IF(Series!AE10="","n.d.",Series!AE10) -> n.d. | F14: =IF(Series!AF10="","n.d.",Series!AF10) -> n.d. | G14: =IF(Series!AG10="","n.d.",Series!AG10) -> n.d. | H14: ='Muestra anterior'!H13 -> 23.6 | I14: =IF(Series!AI10="","n.d.",Series!AI10) -> n.d. | J14: =IF(Series!AJ10="","n.d.",Series!AJ10) -> n.d. | K14: =IF(Series!AK10="","n.d.",Series!AK10) -> n.d.
A15: II-22 | B15: 2022 | C15: Anterior (ID tasas) | D15: =IF(Series!AA11="","n.d.",Series!AA11) -> n.d. | E15: =IF(Series!AE11="","n.d.",Series!AE11) -> n.d. | F15: =IF(Series!AF11="","n.d.",Series!AF11) -> n.d. | G15: =IF(Series!AG11="","n.d.",Series!AG11) -> n.d. | H15: ='Muestra anterior'!H14 -> 19.2 | I15: =IF(Series!AI11="","n.d.",Series!AI11) -> n.d. | J15: =IF(Series!AJ11="","n.d.",Series!AJ11) -> n.d. | K15: =IF(Series!AK11="","n.d.",Series!AK11) -> n.d.
A16: III-22 | B16: 2022 | C16: Vigente | D16: =IF(Series!AA12="","n.d.",Series!AA12) -> 1.4 | E16: =IF(Series!AE12="","n.d.",Series!AE12) -> 0.078212291 | F16: =IF(Series!AF12="","n.d.",Series!AF12) -> n.d. | G16: =IF(Series!AG12="","n.d.",Series!AG12) -> n.d. | H16: =IF(Series!AH12="","n.d.",Series!AH12) -> 23.8 | I16: =IF(Series!AI12="","n.d.",Series!AI12) -> n.d. | J16: =IF(Series!AJ12="","n.d.",Series!AJ12) -> n.d. | K16: =IF(Series!AK12="","n.d.",Series!AK12) -> 36.4
A17: IV-22 | B17: 2022 | C17: Vigente | D17: =IF(Series!AA13="","n.d.",Series!AA13) -> 3.5 | E17: =IF(Series!AE13="","n.d.",Series!AE13) -> 0.20231214 | F17: =IF(Series!AF13="","n.d.",Series!AF13) -> n.d. | G17: =IF(Series!AG13="","n.d.",Series!AG13) -> n.d. | H17: =IF(Series!AH13="","n.d.",Series!AH13) -> 23.7 | I17: =IF(Series!AI13="","n.d.",Series!AI13) -> n.d. | J17: =IF(Series!AJ13="","n.d.",Series!AJ13) -> n.d. | K17: =IF(Series!AK13="","n.d.",Series!AK13) -> 35.2
A18: I-23 | B18: 2023 | C18: Vigente | D18: =IF(Series!AA14="","n.d.",Series!AA14) -> 2 | E18: =IF(Series!AE14="","n.d.",Series!AE14) -> 0.11173184 | F18: =IF(Series!AF14="","n.d.",Series!AF14) -> n.d. | G18: =IF(Series!AG14="","n.d.",Series!AG14) -> n.d. | H18: =IF(Series!AH14="","n.d.",Series!AH14) -> 28.9 | I18: =IF(Series!AI14="","n.d.",Series!AI14) -> n.d. | J18: =IF(Series!AJ14="","n.d.",Series!AJ14) -> n.d. | K18: =IF(Series!AK14="","n.d.",Series!AK14) -> 32.8
A19: II-23 | B19: 2023 | C19: Vigente | D19: =IF(Series!AA15="","n.d.",Series!AA15) -> 0.6 | E19: =IF(Series!AE15="","n.d.",Series!AE15) -> 0.038961039 | F19: =IF(Series!AF15="","n.d.",Series!AF15) -> n.d. | G19: =IF(Series!AG15="","n.d.",Series!AG15) -> n.d. | H19: =IF(Series!AH15="","n.d.",Series!AH15) -> 27.6 | I19: =IF(Series!AI15="","n.d.",Series!AI15) -> n.d. | J19: =IF(Series!AJ15="","n.d.",Series!AJ15) -> n.d. | K19: =IF(Series!AK15="","n.d.",Series!AK15) -> 37.3
A20: III-23 | B20: 2023 | C20: Vigente | D20: =IF(Series!AA16="","n.d.",Series!AA16) -> 1.3 | E20: =IF(Series!AE16="","n.d.",Series!AE16) -> 0.078787879 | F20: =IF(Series!AF16="","n.d.",Series!AF16) -> n.d. | G20: =IF(Series!AG16="","n.d.",Series!AG16) -> n.d. | H20: =IF(Series!AH16="","n.d.",Series!AH16) -> 38.9 | I20: =IF(Series!AI16="","n.d.",Series!AI16) -> n.d. | J20: =IF(Series!AJ16="","n.d.",Series!AJ16) -> n.d. | K20: =IF(Series!AK16="","n.d.",Series!AK16) -> 42
A21: IV-23 | B21: 2023 | C21: Vigente | D21: =IF(Series!AA17="","n.d.",Series!AA17) -> 1 | E21: =IF(Series!AE17="","n.d.",Series!AE17) -> 0.060240964 | F21: =IF(Series!AF17="","n.d.",Series!AF17) -> n.d. | G21: =IF(Series!AG17="","n.d.",Series!AG17) -> n.d. | H21: =IF(Series!AH17="","n.d.",Series!AH17) -> 28.7 | I21: =IF(Series!AI17="","n.d.",Series!AI17) -> n.d. | J21: =IF(Series!AJ17="","n.d.",Series!AJ17) -> n.d. | K21: =IF(Series!AK17="","n.d.",Series!AK17) -> 28.2
A22: I-24 | B22: 2024 | C22: Vigente | D22: =IF(Series!AA18="","n.d.",Series!AA18) -> 1.6 | E22: =IF(Series!AE18="","n.d.",Series!AE18) -> 0.087431694 | F22: =IF(Series!AF18="","n.d.",Series!AF18) -> n.d. | G22: =IF(Series!AG18="","n.d.",Series!AG18) -> n.d. | H22: =IF(Series!AH18="","n.d.",Series!AH18) -> 26.8 | I22: =IF(Series!AI18="","n.d.",Series!AI18) -> n.d. | J22: =IF(Series!AJ18="","n.d.",Series!AJ18) -> n.d. | K22: =IF(Series!AK18="","n.d.",Series!AK18) -> 25.8
A23: II-24 | B23: 2024 | C23: Vigente | D23: =IF(Series!AA19="","n.d.",Series!AA19) -> 0.5 | E23: =IF(Series!AE19="","n.d.",Series!AE19) -> 0.038461538 | F23: =IF(Series!AF19="","n.d.",Series!AF19) -> n.d. | G23: =IF(Series!AG19="","n.d.",Series!AG19) -> n.d. | H23: =IF(Series!AH19="","n.d.",Series!AH19) -> 28 | I23: =IF(Series!AI19="","n.d.",Series!AI19) -> n.d. | J23: =IF(Series!AJ19="","n.d.",Series!AJ19) -> n.d. | K23: =IF(Series!AK19="","n.d.",Series!AK19) -> 34.7
A24: III-24 | B24: 2024 | C24: Vigente | D24: =IF(Series!AA20="","n.d.",Series!AA20) -> 0.9 | E24: =IF(Series!AE20="","n.d.",Series!AE20) -> 0.055900621 | F24: =IF(Series!AF20="","n.d.",Series!AF20) -> n.d. | G24: =IF(Series!AG20="","n.d.",Series!AG20) -> n.d. | H24: =IF(Series!AH20="","n.d.",Series!AH20) -> 41.1 | I24: =IF(Series!AI20="","n.d.",Series!AI20) -> n.d. | J24: =IF(Series!AJ20="","n.d.",Series!AJ20) -> n.d. | K24: =IF(Series!AK20="","n.d.",Series!AK20) -> 40.5
A25: IV-24 | B25: 2024 | C25: Vigente | D25: =IF(Series!AA21="","n.d.",Series!AA21) -> 1.3 | E25: =IF(Series!AE21="","n.d.",Series!AE21) -> 0.097014925 | F25: =IF(Series!AF21="","n.d.",Series!AF21) -> n.d. | G25: =IF(Series!AG21="","n.d.",Series!AG21) -> n.d. | H25: =IF(Series!AH21="","n.d.",Series!AH21) -> 33.7 | I25: =IF(Series!AI21="","n.d.",Series!AI21) -> n.d. | J25: =IF(Series!AJ21="","n.d.",Series!AJ21) -> n.d. | K25: =IF(Series!AK21="","n.d.",Series!AK21) -> 34.3
A26: I-25 | B26: 2025 | C26: Vigente | D26: =IF(Series!AA22="","n.d.",Series!AA22) -> 1 | E26: =IF(Series!AE22="","n.d.",Series!AE22) -> 0.06993007 | F26: =IF(Series!AF22="","n.d.",Series!AF22) -> n.d. | G26: =IF(Series!AG22="","n.d.",Series!AG22) -> n.d. | H26: =IF(Series!AH22="","n.d.",Series!AH22) -> 39.3 | I26: =IF(Series!AI22="","n.d.",Series!AI22) -> n.d. | J26: =IF(Series!AJ22="","n.d.",Series!AJ22) -> n.d. | K26: =IF(Series!AK22="","n.d.",Series!AK22) -> 38.2
A27: II-25 | B27: 2025 | C27: Vigente | D27: =IF(Series!AA23="","n.d.",Series!AA23) -> 0.8 | E27: =IF(Series!AE23="","n.d.",Series!AE23) -> 0.050955414 | F27: =IF(Series!AF23="","n.d.",Series!AF23) -> n.d. | G27: =IF(Series!AG23="","n.d.",Series!AG23) -> n.d. | H27: =IF(Series!AH23="","n.d.",Series!AH23) -> 46.7 | I27: =IF(Series!AI23="","n.d.",Series!AI23) -> n.d. | J27: =IF(Series!AJ23="","n.d.",Series!AJ23) -> n.d. | K27: =IF(Series!AK23="","n.d.",Series!AK23) -> 39.2
... A32: III-26 | B32: 2026 | C32: Vigente | D32: =IF(Series!AA28="","n.d.",Series!AA28) -> n.d. | E32: =IF(Series!AE28="","n.d.",Series!AE28) -> n.d. | F32: =IF(Series!AF28="","n.d.",Series!AF28) -> n.d. | G32: =IF(Series!AG28="","n.d.",Series!AG28) -> n.d. | H32: =IF(Series!AH28="","n.d.",Series!AH28) -> n.d. | I32: =IF(Series!AI28="","n.d.",Series!AI28) -> n.d. | J32: =IF(Series!AJ28="","n.d.",Series!AJ28) -> n.d. | K32: =IF(Series!AK28="","n.d.",Series!AK28) -> n.d.
A33: * ID tasas total: muestra anterior de I-20 a II-22 y diseño vigente desde III-22. Rechazo: el diseño vigente lo publica desde III-22. Por tamaño: solo se tiene el texto del comunicado II-2026 (ID tasas 35.3 vs 53.7); el rechazo por tamaño está pendiente de descargar (SIE CF910).
A35: Cuadro B. Anual 2020-2026 (promedio de trimestres con dato)
A36: Año | B36: Tasa de rechazo — total | C36: Tasa de rechazo — hasta 100 | D36: Tasa de rechazo — más de 100 | E36: ID tasas — total | F36: ID tasas — hasta 100 | G36: ID tasas — más de 100 | H36: Nota
A37: 2020 | B37: =IFERROR(ROUND(AVERAGEIFS($E$6:$E$32,$B$6:$B$32,$A37),5),"n.d.") -> n.d. | C37: =IFERROR(ROUND(AVERAGEIFS($F$6:$F$32,$B$6:$B$32,$A37),5),"n.d.") -> n.d. | D37: =IFERROR(ROUND(AVERAGEIFS($G$6:$G$32,$B$6:$B$32,$A37),5),"n.d.") -> n.d. | E37: =IFERROR(ROUND(AVERAGEIFS($H$6:$H$32,$B$6:$B$32,$A37),3),"n.d.") -> 48.875 | F37: =IFERROR(ROUND(AVERAGEIFS($I$6:$I$32,$B$6:$B$32,$A37),3),"n.d.") -> n.d. | G37: =IFERROR(ROUND(AVERAGEIFS($J$6:$J$32,$B$6:$B$32,$A37),3),"n.d.") -> n.d. | H37: ID tasas: muestra anterior (4 trimestres). Rechazo: no publicado en el diseño vigente.
A38: 2021 | B38: =IFERROR(ROUND(AVERAGEIFS($E$6:$E$32,$B$6:$B$32,$A38),5),"n.d.") -> n.d. | C38: =IFERROR(ROUND(AVERAGEIFS($F$6:$F$32,$B$6:$B$32,$A38),5),"n.d.") -> n.d. | D38: =IFERROR(ROUND(AVERAGEIFS($G$6:$G$32,$B$6:$B$32,$A38),5),"n.d.") -> n.d. | E38: =IFERROR(ROUND(AVERAGEIFS($H$6:$H$32,$B$6:$B$32,$A38),3),"n.d.") -> 36.725 | F38: =IFERROR(ROUND(AVERAGEIFS($I$6:$I$32,$B$6:$B$32,$A38),3),"n.d.") -> n.d. | G38: =IFERROR(ROUND(AVERAGEIFS($J$6:$J$32,$B$6:$B$32,$A38),3),"n.d.") -> n.d. | H38: ID tasas: muestra anterior. Rechazo: no publicado en el diseño vigente.
A39: 2022 | B39: =IFERROR(ROUND(AVERAGEIFS($E$6:$E$32,$B$6:$B$32,$A39),5),"n.d.") -> 0.14026 | C39: =IFERROR(ROUND(AVERAGEIFS($F$6:$F$32,$B$6:$B$32,$A39),5),"n.d.") -> n.d. | D39: =IFERROR(ROUND(AVERAGEIFS($G$6:$G$32,$B$6:$B$32,$A39),5),"n.d.") -> n.d. | E39: =IFERROR(ROUND(AVERAGEIFS($H$6:$H$32,$B$6:$B$32,$A39),3),"n.d.") -> 22.575 | F39: =IFERROR(ROUND(AVERAGEIFS($I$6:$I$32,$B$6:$B$32,$A39),3),"n.d.") -> n.d. | G39: =IFERROR(ROUND(AVERAGEIFS($J$6:$J$32,$B$6:$B$32,$A39),3),"n.d.") -> n.d. | H39: ID tasas: I-II muestra anterior, III-IV diseño vigente. Rechazo: solo III y IV.
A40: 2023 | B40: =IFERROR(ROUND(AVERAGEIFS($E$6:$E$32,$B$6:$B$32,$A40),5),"n.d.") -> 0.07243 | C40: =IFERROR(ROUND(AVERAGEIFS($F$6:$F$32,$B$6:$B$32,$A40),5),"n.d.") -> n.d. | D40: =IFERROR(ROUND(AVERAGEIFS($G$6:$G$32,$B$6:$B$32,$A40),5),"n.d.") -> n.d. | E40: =IFERROR(ROUND(AVERAGEIFS($H$6:$H$32,$B$6:$B$32,$A40),3),"n.d.") -> 31.025 | F40: =IFERROR(ROUND(AVERAGEIFS($I$6:$I$32,$B$6:$B$32,$A40),3),"n.d.") -> n.d. | G40: =IFERROR(ROUND(AVERAGEIFS($J$6:$J$32,$B$6:$B$32,$A40),3),"n.d.") -> n.d.
A41: 2024 | B41: =IFERROR(ROUND(AVERAGEIFS($E$6:$E$32,$B$6:$B$32,$A41),5),"n.d.") -> 0.0697 | C41: =IFERROR(ROUND(AVERAGEIFS($F$6:$F$32,$B$6:$B$32,$A41),5),"n.d.") -> n.d. | D41: =IFERROR(ROUND(AVERAGEIFS($G$6:$G$32,$B$6:$B$32,$A41),5),"n.d.") -> n.d. | E41: =IFERROR(ROUND(AVERAGEIFS($H$6:$H$32,$B$6:$B$32,$A41),3),"n.d.") -> 32.4 | F41: =IFERROR(ROUND(AVERAGEIFS($I$6:$I$32,$B$6:$B$32,$A41),3),"n.d.") -> n.d. | G41: =IFERROR(ROUND(AVERAGEIFS($J$6:$J$32,$B$6:$B$32,$A41),3),"n.d.") -> n.d.
A42: 2025 | B42: =IFERROR(ROUND(AVERAGEIFS($E$6:$E$32,$B$6:$B$32,$A42),5),"n.d.") -> 0.06352 | C42: =IFERROR(ROUND(AVERAGEIFS($F$6:$F$32,$B$6:$B$32,$A42),5),"n.d.") -> n.d. | D42: =IFERROR(ROUND(AVERAGEIFS($G$6:$G$32,$B$6:$B$32,$A42),5),"n.d.") -> n.d. | E42: =IFERROR(ROUND(AVERAGEIFS($H$6:$H$32,$B$6:$B$32,$A42),3),"n.d.") -> 45.65 | F42: =IFERROR(ROUND(AVERAGEIFS($I$6:$I$32,$B$6:$B$32,$A42),3),"n.d.") -> n.d. | G42: =IFERROR(ROUND(AVERAGEIFS($J$6:$J$32,$B$6:$B$32,$A42),3),"n.d.") -> n.d.
A43: 2026 | B43: =IFERROR(ROUND(AVERAGEIFS($E$6:$E$32,$B$6:$B$32,$A43),5),"n.d.") -> 0.23405 | C43: =IFERROR(ROUND(AVERAGEIFS($F$6:$F$32,$B$6:$B$32,$A43),5),"n.d.") -> n.d. | D43: =IFERROR(ROUND(AVERAGEIFS($G$6:$G$32,$B$6:$B$32,$A43),5),"n.d.") -> n.d. | E43: =IFERROR(ROUND(AVERAGEIFS($H$6:$H$32,$B$6:$B$32,$A43),3),"n.d.") -> 42.15 | F43: =IFERROR(ROUND(AVERAGEIFS($I$6:$I$32,$B$6:$B$32,$A43),3),"n.d.") -> 35.3 | G43: =IFERROR(ROUND(AVERAGEIFS($J$6:$J$32,$B$6:$B$32,$A43),3),"n.d.") -> 53.7 | H43: I y II trimestre; III se publica el 19-nov-2026. Por tamaño: solo II-26.
A63: Fuente: Banxico, cuadro 2 de los comunicados III-2022 a II-2026; cálculo propio. Datos: hoja Series, columna de tasa de rechazo.
A82: Fuente: Banxico, cuadro 2 de los comunicados; muestra anterior I-2020 a II-2022 y diseño vigente III-2022 a II-2026. Datos: columna H del Cuadro A.

Sheet Variables
A1: Qué es cada variable, en qué unidad está y si es acumulada
A2: Fuente de las definiciones: comunicados y nota metodológica de Banxico. Todas las preguntas se refieren al trimestre de referencia.
A4: Variable | B4: Qué mide | C4: Unidad | D4: ¿Acumulada? | E4: Periodo con dato | F4: Dónde está en el libro
A5: Usaron nuevo crédito bancario | B5: Empresas que obtuvieron y usaron crédito bancario nuevo durante el trimestre (flujo). | C5: % de empresas | D5: No: solo el trimestre | E5: I-20 a II-26 (I-III 20 muestra anterior) | F5: Series col. H; Serie completa col. H
A6: Con crédito bancario al inicio del trimestre | B6: Empresas que ya tenían crédito bancario vigente al empezar el trimestre (saldo, foto del momento). | C6: % de empresas | D6: No: es una foto, no una suma | E6: I-20 a II-26 | F6: Series col. K-M
A7: No solicitaron crédito | B7: Empresas que no pidieron crédito bancario nuevo en el trimestre. | C7: % de empresas | D7: No | E7: IV-20 a II-26 | F7: Series col. J
A8: Hasta 100 / más de 100 empleados | B8: Corte por tamaño de Banxico. La encuesta cubre empresas de más de 10 empleados; 'hasta 100' = 11 a 100 (pequeñas y parte de las medianas), 'más de 100' = resto de medianas y grandes. | C8: % de empresas de ese tamaño | D8: No | E8: Con crédito: IV-20 a II-26; nuevo crédito: trimestres con dato | F8: Por tamaño
A9: Brecha por tamaño | B9: Más de 100 menos hasta 100 empleados. | C9: Puntos porcentuales (pp) | D9: No | E9: IV-20 a II-26 | F9: Series col. N y Q
A10: Condiciones: ninguna / menor / mayor limitante | B10: Cómo califican las empresas las condiciones de acceso al crédito bancario. | C10: % de empresas (suman 100) | D10: No | E10: IV-20 a II-26 | F10: Series col. R-T
A11: Fuentes de financiamiento | B11: Empresas que usaron cada fuente (proveedores, banca comercial, grupo corporativo, etc.). Respuesta múltiple: no suman 100. | C11: % de empresas | D11: No | E11: III-22 a II-26 | F11: Series col. U-Y
A12: Solicitaron y rechazado | B12: Empresas cuya solicitud de crédito fue rechazada en el trimestre. | C12: % del total de empresas | D12: No | E12: III-22 a II-26 | F12: Series col. AA
A13: Tasa de rechazo | B13: Rechazadas / (rechazadas + empresas que usaron crédito nuevo). Cálculo propio. | C13: % de solicitudes resueltas | D13: No | E13: III-22 a II-26 | F13: Series col. AE; Rechazo y costo
A14: Índice de difusión de costo (tasas, comisiones) | B14: Saldo de opiniones de quienes usaron crédito nuevo: >50 = más barato que el trimestre previo, <50 = más caro. | C14: Índice 0-100 | D14: No: compara con el trimestre anterior | E14: Tasas: I-20 a II-26 (hasta II-22 muestra anterior) | F14: Series col. AH-AK
A15: Problema más apremiante | B15: Problema principal que reporta la empresa (ventas, acceso al financiamiento, etc.). | C15: % de empresas | D15: No | E15: III-22 a II-26 | F15: Series col. AM-AN
... A19: Promedio anual | B19: Promedio simple de los trimestres del año con dato. | C19: Igual que la variable | D19: Es un promedio, no una suma | E19: 2020-2026 | F19: Resumen anual
A21: Respuesta a '¿la información es acumulada?': no. Cada comunicado trimestral reporta lo que pasó en ese trimestre; el IV trimestre no es el total del año. Para un dato anual se promedian los trimestres (hoja Resumen anual).

Sheet Hipótesis
A1: Hipótesis 2020-2026 y resultado preliminar
A2: Cada hipótesis se prueba con las series de este libro. 'Pendiente' = falta el dato para probarla.
A4: # | B4: Hipótesis | C4: Indicador | D4: Dato clave (fórmula) | E4: Resultado preliminar
A5: H1 | B5: Entre 2020 y 2026 cae el flujo de crédito bancario nuevo a empresas, mientras el saldo (empresas con crédito) se mantiene. | C5: Usaron nuevo crédito; con crédito al inicio | D5: ="Nuevo: "&TEXT('Resumen anual'!D9,"0.0")&"% (2023) → "&TEXT('Resumen anual'!D12,"0.0")&"% (2026). Saldo: "&TEXT('Resumen anual'!F9,"0.0")&"% → "&TEXT('Resumen anual'!F12,"0.0")&"%" -> Nuevo: 15.4% (2023) → 12.2% (2026). Saldo: 37.8% → 37.2% | E5: Se sostiene desde 2023. En 2020 la caída fue por la pandemia (muestra anterior: 24.2% en I-20 a 16.8% en IV-20).
A6: H2 | B6: La caída se concentra en las empresas de 11 a 100 empleados; las de más de 100 mantienen su acceso y la brecha se abre. | C6: Brecha por tamaño (con crédito y nuevo crédito) | D6: ="Brecha con crédito: "&TEXT('Por tamaño'!D40,"0.0")&" pp (2023) → "&TEXT('Por tamaño'!D43,"0.0")&" pp (2026)" -> Brecha con crédito: 6.8 pp (2023) → 12.4 pp (2026) | E6: Se sostiene: la brecha sube cada año desde 2023 y en II-26 el nuevo crédito de pymes (9.9%) es menos de la mitad que el de grandes (21.6%).
A7: H3 | B7: Los recortes de Banxico (2024-2026) no se tradujeron en más crédito nuevo ni en un costo percibido menor. | C7: Nuevo crédito por fase; ID tasas; TIIE | D7: ="Nuevo crédito: meseta "&TEXT(Estadísticas!C22,"0.0")&"% vs recortes "&TEXT(Estadísticas!C23,"0.0")&"%. Correlación "&TEXT(Estadísticas!B12,"+0.00") -> Nuevo crédito: meseta 15.2% vs recortes 13.6%. Correlación +0.46 | E7: Se sostiene en parte: el costo percibido mejoró hasta III-25 (49.0) y volvió a empeorar en 2026 (39.4). La TIIE falta de capturar.
A8: H4 | B8: En 2026 los bancos endurecieron la oferta: sube el rechazo y pega más a las pymes. | C8: Tasa de rechazo, total y por tamaño | D8: ="Rechazo 2026: "&TEXT('Resumen anual'!Q12,"0.0%")&" vs "&TEXT('Resumen anual'!Q11,"0.0%")&" en 2025" -> Rechazo 2026: 23.4% vs 6.4% en 2025 | E8: Primera parte se sostiene (22.5% y 24.3% en I y II-26). Por tamaño: pendiente (falta el rechazo por tamaño).
A9: H5 | B9: La restricción principal es de demanda (ventas, situación económica), no de acceso al crédito. | C9: Problema más apremiante; no solicitaron | D9: ="II-26: ventas "&TEXT(Series!AM27,"0.0")&"% vs acceso "&TEXT(Series!AN27,"0.0")&"%; no solicitaron "&TEXT(Series!J27,"0.0")&"%" -> II-26: ventas 44.6% vs acceso 1.2%; no solicitaron 82.1% | E9: Se sostiene.
A10: H6 | B10: Las empresas exportadoras tienen más acceso a crédito bancario que las no exportadoras. | C10: Nuevo crédito y con crédito por actividad exportadora | D10: Pendiente | E10: Pendiente: el corte por exportadoras no está en los datos capturados (ver hoja Pendientes).

Sheet Datos de imágenes
A1: Base de datos de las gráficas de los documentos
A2: Para cada imagen: qué muestra, dónde están sus datos en este libro y la fuente original.
A4: Figura | B4: Documento | C4: Qué muestra | D4: Datos en | E4: Fuente original
A5: SS2 · Figura 1 | B5: Servicio social 2, sección 2 | C5: Fuentes a las que acudieron las empresas que pidieron financiamiento, 2022-2024 (% de solicitantes, respuesta múltiple) | D5: Esta hoja, tabla ENAFIN (abajo) | E5: INEGI-CNBV, ENAFIN 2024, reporte de resultados (28-may-2025)
A6: SS2 · Figura 2 = Banxico · Gráfica 1 | B6: Ambos documentos (crédito nuevo) | C6: Crédito bancario nuevo 2020-2026 por trimestre y tendencia lineal desde I-23 | D6: Serie completa 2020-2026, col. L-O | E6: Banxico, comunicados de la encuesta (muestra anterior y diseño vigente)
A7: Banxico · Gráfica 2 | B7: Banxico (crédito nuevo) | C7: Crédito nuevo por año 2020-2026: promedio de trimestres vs IV trimestre | D7: Resumen anual, col. D-E | E7: Banxico, comunicados de la encuesta
A8: SS2 · Figura 3 = Banxico · Gráfica 3 | B8: Ambos documentos (brecha) | C8: Con crédito y crédito nuevo por tamaño: pymes vs grandes, con tendencia | D8: Series, col. L-M y O-P | E8: Banxico, comunicados de la encuesta, diseño vigente
A9: Banxico · Gráfica 4 | B9: Banxico (brecha) | C9: Brecha por tamaño por año 2020-2026 | D9: Por tamaño, Cuadro C | E9: Cálculo propio con datos de Banxico
A10: Banxico · Gráfica 5 | B10: Banxico (rechazo y costo) | C10: Tasa de rechazo trimestral e índice de costo 2020-2026 | D10: Rechazo y costo, Cuadro A | E10: Banxico, cuadro 2 de los comunicados; cálculo propio
A13: Tabla ENAFIN (SS2 · Figura 1)
A14: Fuente a la que acudió | B14: % de empresas solicitantes
A15: Bancos / banca comercial | B15: 82.8
A16: Proveedores | B16: 28.5
A17: Familiares o amistades | B17: 12.7
A18: Uniones de crédito | B18: 1.9
A19: Banca de desarrollo | B19: 0.9
A20: Crowdfunding | B20: 0.5
A22: Fuente: INEGI-CNBV, Encuesta Nacional de Financiamiento de las Empresas (ENAFIN) 2024, reporte de resultados del 28 de mayo de 2025. Empresas con 6 o más personas ocupadas en localidades de 50 mil habitantes o más. https://www.inegi.org.mx/contenidos/saladeprensa/boletines/2025/enafin/ENAFIN_24_RR.pdf

Sheet Estadísticas
A1: Estadísticos del nuevo crédito bancario y relación con la tasa
A2: Diseño vigente, IV-2020 al último trimestre publicado (II-2026). Las celdas vacías de III-2026 se ignoran.
A4: Indicador | B4: Valor
A5: Promedio IV-20 a II-26 | B5: =AVERAGE(Series!$H$5:$H$28) -> 13.882609
A6: Desviación estándar | B6: =STDEV(Series!$H$5:$H$28) -> 2.0715941
A7: Mínimo | B7: =MIN(Series!$H$5:$H$28) -> 9
A8: Trimestre del mínimo | B8: =INDEX(Series!$A$5:$A$28,MATCH(MIN(Series!$H$5:$H$28),Series!$H$5:$H$28,0)) -> IV-21
A9: Lugar de II-26 (1 = más bajo) | B9: =RANK(Series!H27,Series!$H$5:$H$28,1) -> 3
A10: Máximo | B10: =MAX(Series!$H$5:$H$28) -> 16.7
A11: Pendiente desde I-23 (pp por año) | B11: =SLOPE(Series!H14:H28,Series!E14:E28)*4 -> -1.0312088
A12: Correlación nuevo crédito vs tasa (mismo trimestre) | B12: =CORREL(Series!H5:H27,Series!F5:F27) -> 0.45537086
A13: Correlación con tasa rezagada 1 trimestre | B13: =CORREL(Series!H6:H27,Series!F5:F26) -> 0.41933076
A14: Error de muestreo 95% de un trimestre (pp, muestreo aleatorio simple, n=650, p=promedio) | B14: =1.96*SQRT(B5/100*(1-B5/100)/650)*100 -> 2.6581554
A15: Brecha por tamaño máxima (pp) | B15: =MAX(Series!$N$5:$N$28) -> 19.1
A16: Trimestre de la brecha máxima | B16: =INDEX(Series!$A$5:$A$28,MATCH(B15,Series!$N$5:$N$28,0)) -> IV-21
A17: El error real es mayor: la encuesta usa factores de expansión y estratos (efecto de diseño > 1).
A19: Fase de política monetaria | B19: Trimestres con dato | C19: Nuevo crédito promedio | D19: Tasa promedio fin de trimestre | E19: Sin limitante promedio | F19: Periodo
A20: 1 Pre-alzas | B20: =COUNTIFS(Series!$D$5:$D$28,$A20,Series!$H$5:$H$28,"<>") -> 2 | C20: =IFERROR(AVERAGEIFS(Series!$H$5:$H$28,Series!$D$5:$D$28,$A20),"n.d.") -> 14.55 | D20: =IFERROR(AVERAGEIFS(Series!$F$5:$F$28,Series!$D$5:$D$28,$A20),"n.d.") -> 4.125 | E20: =IFERROR(AVERAGEIFS(Series!$R$5:$R$28,Series!$D$5:$D$28,$A20),"n.d.") -> 49.45 | F20: IV-20 a I-21 (tasa 4.00-4.25%)
A21: 2 Alzas | B21: =COUNTIFS(Series!$D$5:$D$28,$A21,Series!$H$5:$H$28,"<>") -> 8 | C21: =IFERROR(AVERAGEIFS(Series!$H$5:$H$28,Series!$D$5:$D$28,$A21),"n.d.") -> 13.6 | D21: =IFERROR(AVERAGEIFS(Series!$F$5:$F$28,Series!$D$5:$D$28,$A21),"n.d.") -> 7.46875 | E21: =IFERROR(AVERAGEIFS(Series!$R$5:$R$28,Series!$D$5:$D$28,$A21),"n.d.") -> 54.4125 | F21: II-21 a I-23 (15 alzas, 4.25% → 11.25%)
A22: 3 Meseta 11.25% | B22: =COUNTIFS(Series!$D$5:$D$28,$A22,Series!$H$5:$H$28,"<>") -> 3 | C22: =IFERROR(AVERAGEIFS(Series!$H$5:$H$28,Series!$D$5:$D$28,$A22),"n.d.") -> 15.2 | D22: =IFERROR(AVERAGEIFS(Series!$F$5:$F$28,Series!$D$5:$D$28,$A22),"n.d.") -> 11.25 | E22: =IFERROR(AVERAGEIFS(Series!$R$5:$R$28,Series!$D$5:$D$28,$A22),"n.d.") -> 57.566667 | F22: II-23 a IV-23
A23: 4 Recortes | B23: =COUNTIFS(Series!$D$5:$D$28,$A23,Series!$H$5:$H$28,"<>") -> 10 | C23: =IFERROR(AVERAGEIFS(Series!$H$5:$H$28,Series!$D$5:$D$28,$A23),"n.d.") -> 13.58 | D23: =IFERROR(AVERAGEIFS(Series!$F$5:$F$28,Series!$D$5:$D$28,$A23),"n.d.") -> 8.725 | E23: =IFERROR(AVERAGEIFS(Series!$R$5:$R$28,Series!$D$5:$D$28,$A23),"n.d.") -> 55.08 | F23: I-24 a II-26 (11.00% → 6.50%)
A24: 5 Pausa 6.50% | B24: =COUNTIFS(Series!$D$5:$D$28,$A24,Series!$H$5:$H$28,"<>") -> 0 | C24: =IFERROR(AVERAGEIFS(Series!$H$5:$H$28,Series!$D$5:$D$28,$A24),"n.d.") -> n.d. | D24: =IFERROR(AVERAGEIFS(Series!$F$5:$F$28,Series!$D$5:$D$28,$A24),"n.d.") -> 6.5 | E24: =IFERROR(AVERAGEIFS(Series!$R$5:$R$28,Series!$D$5:$D$28,$A24),"n.d.") -> n.d. | F24: III-26 (encuesta pendiente: 19-nov-2026)
A26: Las alzas empezaron en junio de 2021 (II-21). Correlación positiva no implica causalidad: incluye la recuperación pospandemia.

Sheet Muestra anterior
A1: Muestra anterior (≥450 empresas) vs diseño vigente — trimestres traslapados
A2: La muestra anterior es la única que cubre I a III de 2020. Sirve para ver la dirección; no se empalma en niveles con el diseño vigente.
A4: Trimestre | B4: Nuevo crédito — muestra anterior | C4: Nuevo crédito — diseño vigente | D4: Diferencia (pp) | E4: Con crédito — muestra anterior | F4: Con crédito — diseño vigente | G4: Diferencia (pp) | H4: ID tasas — muestra anterior | I4: Sin limitante — muestra anterior
A5: I-20 | B5: 24.2 | E5: 47.6 | H5: 61.1 | I5: 54.5
A6: II-20 | B6: 21.6 | E6: 47.5 | H6: 38.5 | I6: 48.1
A7: III-20 | B7: 19 | E7: 46.9 | H7: 50.8 | I7: 48.5
A8: IV-20 | B8: 16.8 | C8: =Series!H5 -> 13.6 | D8: =B8-C8 -> 3.2 | E8: 43.9 | F8: =Series!K5 -> 39.7 | G8: =E8-F8 -> 4.2 | H8: 45.1 | I8: 50.2
A9: I-21 | B9: 20.8 | C9: =Series!H6 -> 15.5 | D9: =B9-C9 -> 5.3 | E9: 46 | F9: =Series!K6 -> 39.1 | G9: =E9-F9 -> 6.9 | H9: 52.8 | I9: 57.6
A10: II-21 | B10: 17.4 | C10: =Series!H7 -> 11 | D10: =B10-C10 -> 6.4 | E10: 43.6 | F10: =Series!K7 -> 36.6 | G10: =E10-F10 -> 7 | H10: 32.6 | I10: 62.2
A11: III-21 | B11: 19.3 | C11: =Series!H8 -> 11.5 | D11: =B11-C11 -> 7.8 | E11: 46.5 | F11: =Series!K8 -> 37.5 | G11: =E11-F11 -> 9 | H11: 33.8 | I11: 55.5
A12: IV-21 | B12: 17.8 | C12: =Series!H9 -> 9 | D12: =B12-C12 -> 8.8 | E12: 48.4 | F12: =Series!K9 -> 37.5 | G12: =E12-F12 -> 10.9 | H12: 27.7 | I12: 55.6
A13: I-22 | B13: 19.5 | C13: =Series!H10 -> 15.2 | D13: =B13-C13 -> 4.3 | E13: 46 | F13: =Series!K10 -> 41.9 | G13: =E13-F13 -> 4.1 | H13: 23.6 | I13: 55.5
A14: II-22 | B14: 21 | C14: =Series!H11 -> 15.9 | D14: =B14-C14 -> 5.1 | E14: 47 | F14: =Series!K11 -> 40.2 | G14: =E14-F14 -> 6.8 | H14: 19.2 | I14: 53.7
A16: Promedio dif. | D16: =AVERAGE(D8:D14) -> 5.8428571 | G16: =AVERAGE(G8:G14) -> 6.9857143
A17: Rango dif. | D17: =TEXT(MIN(D8:D14),"0.0")&" a "&TEXT(MAX(D8:D14),"0.0") -> 3.2 a 8.8 | G17: =TEXT(MIN(G8:G14),"0.0")&" a "&TEXT(MAX(G8:G14),"0.0") -> 4.1 a 10.9
A18: Promedio 2020 (I-IV), muestra anterior | B18: =ROUND(AVERAGE(B5:B8),3) -> 20.4 | E18: =ROUND(AVERAGE(E5:E8),3) -> 46.475 | H18: =ROUND(AVERAGE(H5:H8),3) -> 48.875 | I18: =ROUND(AVERAGE(I5:I8),3) -> 50.325
A20: Fuente: Banxico, comunicados I-2021 (series I-19 a I-21) y II-2022 (II-20 a II-22), muestra anterior; diseño vigente: hoja Series.

Sheet Pendientes
A1: Datos pendientes y dónde obtenerlos
A2: Al capturar estos datos en las celdas amarillas de la hoja Series, todas las tablas y gráficas se actualizan.
A4: Dato | B4: Por qué falta | C4: Dónde obtenerlo | D4: Cuándo
A5: Encuesta III-2026 (julio-septiembre) | B5: Banxico aún no la publica. | C5: Comunicado 'Evolución trimestral del financiamiento a las empresas', julio-septiembre 2026 | D5: 19-nov-2026, 9:00 h
A6: TIIE 28 días por trimestre 2020-2026 | B6: No se pudo descargar del SIE en esta revisión. | C6: SIE de Banxico, serie SF43783 (TIIE a 28 días); tomar el último día hábil de cada trimestre | D6: Disponible
A7: Nuevo crédito por tamaño en trimestres I y III (2021-2025) | B7: Solo se capturaron los comunicados de II y IV trimestre, más I-24 e I-26. | C7: SIE CF910 o comunicados de mayo y noviembre de cada año (cuadro 2) | D7: Disponible
A8: Tasa de rechazo por tamaño | B8: No se capturó del cuadro 2. | C8: Cuadro 2 de cada comunicado (columnas por tamaño) / SIE CF910 | D8: Disponible
A9: ID tasas y banca comercial por tamaño (antes de II-26) | B9: Solo se tiene el texto de II-26. | C9: Cuadros 1 y 2 de cada comunicado / SIE CF910 | D9: Disponible
A10: Componente de exportaciones | B10: El corte exportadoras / no exportadoras no está en los datos capturados; la muestra anterior lo publicaba y hay que confirmar si el diseño vigente lo conserva. | C10: SIE CF910 (buscar series por actividad exportadora) y cuadros de los comunicados | D10: Por verificar
A11: 2020 I-III por tamaño | B11: La muestra anterior usaba otros estratos de tamaño y no se capturaron. | C11: Comunicado I-2021 (muestra anterior), cuadros por tamaño | D11: Disponible

Sheet Verificación
A1: Verificación de las cifras y de las correcciones
A2: Parte 1: cifras del análisis previo. Parte 2: correcciones del asesor (octubre 2026).
A4: Afirmación del análisis previo | B4: Valor citado | C4: Valor verificado | D4: Estado | E4: Comentario
A5: Nuevo crédito promedio 2021-2026 y desv. est. | B5: 13.9 / 2.1 | C5: 13.9 / 2.1 | D5: Correcto | E5: Coincide con la serie del diseño vigente.
A6: 11.2% es el 3er valor más bajo (tras 9.0 IV-21 y 11.0 II-21) | B6: 3º | C6: 3º | D6: Correcto
A7: Brecha máxima por tamaño 19.1 pp en IV-21 | B7: 19.1 | C7: 19.1 | D7: Correcto | E7: 54.4% grandes vs 35.3% chicas.
A8: Resumen anual (nuevo crédito, con crédito por tamaño, sin limitante) | B8: tabla | C8: tabla | D8: Correcto | E8: Todos los promedios coinciden (ver hoja Resumen anual).
A9: Tendencia desde I-23 | B9: -1.0 pp/año | C9: -1.0 pp/año | D9: Correcto
A10: Grandes con crédito en 2021: 52-54% | B10: 52-54 | C10: 48.6-54.4 | D10: Matizar | E10: II-21 fue 48.6%.
A11: Fuentes de crédito: proveedores 58-65% | B11: 58-65 | C11: 56.4-64.9 | D11: Matizar | E11: III-25 bajó a 56.4%.
A12: Banca comercial pasó de 32.3% (IV-23) a 24.5% | B12: 32.3 → 24.5 | C12: 32.3 → 24.5 | D12: Correcto | E12: 24.5% es el nivel más bajo desde III-22.
A13: Ventas subió de 29.4% (IV-23) a 44.6% | B13: 29.4 → 44.6 | C13: 29.4 → 44.6 | D13: Matizar | E13: El pico fue 47.8% en II-25; desde ahí está estable en 42-45%.
A14: Acceso al financiamiento nunca pasa de 2.6% | B14: ≤2.6 | C14: ≤2.6 | D14: Correcto | E14: III-22 a II-26.
A15: Rechazos (orden y valores) | B15: IV-23 6%, I-24 9%, IV-22 20%, II-26 24% | C15: Serie completa | D15: Corregir | E15: El orden estaba revuelto. Lo relevante: I-26 (22.5%) y II-26 (24.3%) son los dos valores más altos desde III-22; antes oscilaba 3-11%, salvo IV-22 (20.2%).
A16: Índice de tasas: 'solo tengo estos puntos' | B16: 6 puntos | C16: Serie III-22 a II-26 | D16: Corregir | E16: Serie completa: subió hasta 49.0 en III-25 y bajó a 44.9 (I-26) y 39.4 (II-26). El costo percibido empeoró en 2026 pese a los recortes.
A17: Tabla de fases: 'Alzas II-22 a I-23' | B17: II-22 a I-23 | C17: II-21 a I-23 | D17: Corregir | E17: Las alzas empezaron en junio de 2021. Promedios recalculados en hoja Estadísticas.
A18: Tasas de fin de trimestre 'estimadas' | B18: estimadas | C18: reconstruidas de anuncios | D18: Matizar | E18: Ver columna E de Series; I-26 = 6.75%, II-26 = 6.50%.
A19: Correlación nuevo crédito vs tasa | B19: +0.46 | C19: +0.46 | D19: Correcto | E19: Con tasa rezagada un trimestre: +0.42. No implica causalidad.
A20: 2020 muestra anterior (I-20 24.2 ... IV-20 16.8; vigente 47.6 ... 43.9) | B20: tabla | C20: tabla | D20: Correcto | E20: Comunicado I-2021.
A21: Diferencia entre muestras: ~6 pp nuevo crédito (3-9), 4-11 pp vigente | B21: ~6 / 4-11 | C21: 5.8 / 4.1-10.9 | D21: Correcto | E21: Traslape IV-20 a II-22.
A22: 'Para series largas usar solo IV-20 en adelante' vs tabla 2020 con IV-20 | B22: contradicción | C22: IV-20 existe en ambas | D22: Matizar | E22: IV-20 tiene dos valores: 16.8% (muestra anterior) y 13.6% (diseño vigente).
A23: Esperan pedir crédito bancario: 20.3% (antes 18.7%) | B23: 20.3 | C23: 20.3 | D23: Correcto
A24: Próxima publicación 19-nov-2026 (julio-septiembre) | B24: 19-nov | C24: 19-nov | D24: Correcto | E24: Calendario Banxico 2026.
A25: Banxico en 6.50% en septiembre 2026 | B25: 6.50 | C25: 6.50 | D25: Correcto | E25: Decisión del 24-sep-2026; tercera pausa consecutiva.
A28: Parte 2. Correcciones del asesor
A29: Corrección pedida | B29: Qué se hizo | C29: Dónde | D29: Estado | E29: Comentario
A30: Gráfica del cuadro de la página 3 (brecha por tamaño) | B30: Gráficas de pymes vs grandes con tendencia y brecha anual | C30: Por tamaño; Word Banxico | D30: Hecho
A31: Base de datos de las fuentes de las imágenes | B31: Hoja con los datos de cada figura y su fuente | C31: Datos de imágenes | D31: Hecho
A32: Hipótesis 2020-2026 | B32: Seis hipótesis con su dato clave | C32: Hipótesis; ambos Word | D32: Hecho | E32: H4 por tamaño y H6 quedan pendientes de dato.
A33: Base y gráfico de tendencia de la encuesta | B33: Serie completa con tendencia lineal | C33: Serie completa 2020-2026 | D33: Hecho
A34: Una para grandes y otra para pymes | B34: Gráficas por tamaño con tendencia | C34: Por tamaño | D34: Hecho
A35: Cuadro gran empresa y cuadro medianas y pequeñas | B35: Cuadros A y B trimestrales y Cuadro C anual | C35: Por tamaño | D35: Hecho | E35: Huecos donde no hay dato publicado.
A36: Componente de exportaciones | B36: Sección y fila de pendientes | C36: Pendientes; Word Banxico | D36: Pendiente de dato | E36: Requiere descargar del SIE.
A37: Crédito nuevo por año 2020 a III-2026 | B37: Resumen anual 2020-2026 y 2020 por trimestre | C37: Resumen anual; Serie completa | D37: Hecho (III-26 pendiente) | E37: III-26 se publica el 19-nov-2026.
A38: Brecha por tamaño por año 2020-26 | B38: Cuadro C | C38: Por tamaño | D38: Hecho | E38: 2020 = solo IV-20.
A39: Rechazo y costo por pymes, grandes y anual | B39: Cuadros A y B | C39: Rechazo y costo | D39: Parcial | E39: Por tamaño solo II-26 (costo).
A40: Añadir la TIIE | B40: Columna en Series, Serie completa y Resumen anual | C40: Series col. G | D40: Pendiente de dato | E40: Celdas amarillas; serie SF43783.
A41: Variables: qué son, porcentaje | B41: Hoja de variables y unidades | C41: Variables | D41: Hecho
A42: Serie completa 2020-2026 y tercer trimestre 2026 | B42: 27 trimestres I-20 a III-26 | C42: Serie completa 2020-2026 | D42: Hecho (III-26 pendiente)
A43: Revisar si la información es acumulada / IV trimestre | B43: No es acumulada; se muestra el IV trimestre junto al promedio anual | C43: Resumen anual col. E; Variables | D43: Hecho
A44: Fuente debajo de cada gráfica | B44: Línea 'Fuente:' bajo cada gráfica del libro y de los Word | C44: Todas | D44: Hecho
A45: 2020: faltaban I, II y III trimestre | B45: Se agregan desde la muestra anterior, marcados | C45: Serie completa; Resumen anual | D45: Hecho | E45: No comparables en nivel con el diseño vigente.

Sheet Fuentes
A1: Fuentes
A2: Comunicados de Banxico y notas citadas.
A4: Comunicado | B4: Uso | C4: URL
A5: II-2026 (20-ago-2026) | B5: Series II-24 a II-26; cuadros I-26 y II-26 | C5: https://www.banxico.org.mx/publicaciones-y-prensa/evolucion-trimestral-del-financiamiento-a-las-empr/{E337ADB1-E981-1E18-A430-CEF8FF7A5164}.pdf
A6: IV-2025 (19-feb-2026) | B6: Series IV-23 a IV-25; cuadros III-25 y IV-25 | C6: https://www.banxico.org.mx/publicaciones-y-prensa/evolucion-trimestral-del-financiamiento-a-las-empr/{6353FB17-0AEC-FEC4-C353-23DA19D12758}.pdf
A7: II-2025 (21-ago-2025) | B7: Cuadros I-25 y II-25 | C7: https://www.banxico.org.mx/publicaciones-y-prensa/evolucion-trimestral-del-financiamiento-a-las-empr/{A359AF39-1AA0-580C-3CEF-9373F9D485D8}.pdf
A8: IV-2024 (20-feb-2025) | B8: Cuadros III-24 y IV-24 | C8: https://www.banxico.org.mx/publicaciones-y-prensa/evolucion-trimestral-del-financiamiento-a-las-empr/{41E9A188-3BBF-92FE-3901-BFCF227A03C1}.pdf
A9: II-2024 (22-ago-2024) | B9: Series II-22 a II-24; cuadros I-24 y II-24 | C9: https://www.banxico.org.mx/publicaciones-y-prensa/evolucion-trimestral-del-financiamiento-a-las-empr/{C03F13AB-9577-CCE0-8FE6-66CD253255B7}.pdf
A10: IV-2023 (22-feb-2024) | B10: Series IV-21 a IV-23; cuadros III-23 y IV-23 | C10: https://www.banxico.org.mx/publicaciones-y-prensa/evolucion-trimestral-del-financiamiento-a-las-empr/{E2598EEE-1219-84C2-FA87-EC08CD410AF0}.pdf
A11: II-2023 (17-ago-2023) | B11: Cuadros I-23 y II-23 | C11: https://www.banxico.org.mx/publicaciones-y-prensa/evolucion-trimestral-del-financiamiento-a-las-empr/{0CE3D5CB-D226-BD23-14DD-FF6866A972C4}.pdf
A12: IV-2022 (16-feb-2023) | B12: Primer comunicado con diseño vigente; series IV-20 a IV-22; cuadros III-22 y IV-22 | C12: https://www.banxico.org.mx/publicaciones-y-prensa/evolucion-trimestral-del-financiamiento-a-las-empr/{D5CA1289-F2D7-09C2-7B2D-423C8E37F21D}.pdf
A13: II-2022 (18-ago-2022) | B13: Muestra anterior: II-20 a II-22 | C13: https://www.banxico.org.mx/publicaciones-y-prensa/evolucion-trimestral-del-financiamiento-a-las-empr/{FB5B2684-8343-D0B7-062D-8CBD1E9275CA}.pdf
A14: I-2021 (20-may-2021) | B14: Muestra anterior: I-19 a I-21 | C14: https://www.banxico.org.mx/publicaciones-y-prensa/evolucion-trimestral-del-financiamiento-a-las-empr/{2F0797C9-2616-D11A-47F5-39FE48B68D31}.pdf
A15: Nota metodológica | B15: Referencia | C15: https://www.banxico.org.mx/apps/sie/{9F0C92AB-EEAE-142D-4CC8-EC8DC2F2A7AD}.pdf
... A23: ENAFIN 2024 (INEGI-CNBV) | B23: Datos de la Fig. 1 del documento de servicio social | C23: https://www.inegi.org.mx/contenidos/saladeprensa/boletines/2025/enafin/ENAFIN_24_RR.pdf
